[
    {
        "recommendationid": "143881739",
        "author": {
            "steamid": "76561198843809046",
            "num_games_owned": 0,
            "num_reviews": 4,
            "playtime_forever": 22,
            "playtime_last_two_weeks": 22,
            "playtime_at_review": 22,
            "last_played": 1691753523
        },
        "language": "schinese",
        "review": "你说的对，但是《守望先锋》是由暴雪娱乐自主研发的一款多人网络射击游戏。游戏以未来地球为背景，讲述人类、守望先锋成员和智能机械的恩怨纠葛。游戏中有输出、重装、支援三种类型，总计32位风格迥异的英雄可以选择，还有29张地图可供战斗。玩家将控制许多风格迥异的英雄中的其中一个",
        "timestamp_created": 1691756629,
        "timestamp_updated": 1691756629,
        "voted_up": false,
        "votes_up": 0,
        "votes_funny": 0,
        "weighted_vote_score": 0,
        "comment_count": 0,
        "steam_purchase": false,
        "received_for_free": false,
        "written_during_early_access": false,
        "hidden_in_steam_china": true,
        "steam_china_location": ""
    },
    {
        "recommendationid": "143881738",
        "author": {
            "steamid": "76561198103175123",
            "num_games_owned": 186,
            "num_reviews": 32,
            "playtime_forever": 61,
            "playtime_last_two_weeks": 61,
            "playtime_at_review": 23,
            "last_played": 1691761051
        },
        "language": "schinese",
        "review": "我收到了召唤，我必须差评，一如既往",
        "timestamp_created": 1691756629,
        "timestamp_updated": 1691756629,
        "voted_up": false,
        "votes_up": 0,
        "votes_funny": 0,
        "weighted_vote_score": 0,
        "comment_count": 0,
        "steam_purchase": false,
        "received_for_free": false,
        "written_during_early_access": false,
        "hidden_in_steam_china": true,
        "steam_china_location": ""
    },
    {
        "recommendationid": "143881737",
        "author": {
            "steamid": "76561199108601911",
            "num_games_owned": 223,
            "num_reviews": 68,
            "playtime_forever": 52,
            "playtime_last_two_weeks": 52,
            "playtime_at_review": 52,
            "last_played": 1691756418
        },
        "language": "english",
        "review": "go back to your worst launcher in the world. why did you come to steam?? have online sales also fallen???? did you destroy the game yourself and hope that the steam community will help you? nothing else will help you. it was necessary to immediately release the game on steam when it was released.",
        "timestamp_created": 1691756627,
        "timestamp_updated": 1691756627,
        "voted_up": false,
        "votes_up": 1,
        "votes_funny": 0,
        "weighted_vote_score": "0.500831961631774902",
        "comment_count": 0,
        "steam_purchase": false,
        "received_for_free": false,
        "written_during_early_access": false,
        "hidden_in_steam_china": true,
        "steam_china_location": ""
    },
    {
        "recommendationid": "143881735",
        "author": {
            "steamid": "76561199101039460",
            "num_games_owned": 41,
            "num_reviews": 3,
            "playtime_forever": 85,
            "playtime_last_two_weeks": 85,
            "playtime_at_review": 85,
            "last_played": 1691756580
        },
        "language": "schinese",
        "review": "只能说游戏虽好，暴雪该吃粑粑还是得吃",
        "timestamp_created": 1691756626,
        "timestamp_updated": 1691756626,
        "voted_up": false,
        "votes_up": 0,
        "votes_funny": 0,
        "weighted_vote_score": 0,
        "comment_count": 0,
        "steam_purchase": false,
        "received_for_free": false,
        "written_during_early_access": false,
        "hidden_in_steam_china": true,
        "steam_china_location": ""
    },
    {
        "recommendationid": "143881734",
        "author": {
            "steamid": "76561198874821911",
            "num_games_owned": 30,
            "num_reviews": 5,
            "playtime_forever": 273,
            "playtime_last_two_weeks": 273,
            "playtime_at_review": 159,
            "last_played": 1691763515
        },
        "language": "schinese",
        "review": "呵呵哒，不好说，但就是不喜欢了。",
        "timestamp_created": 1691756626,
        "timestamp_updated": 1691756626,
        "voted_up": false,
        "votes_up": 0,
        "votes_funny": 0,
        "weighted_vote_score": 0,
        "comment_count": 0,
        "steam_purchase": false,
        "received_for_free": false,
        "written_during_early_access": false,
        "hidden_in_steam_china": true,
        "steam_china_location": ""
    },
    {
        "recommendationid": "143881731",
        "author": {
            "steamid": "76561198317859013",
            "num_games_owned": 0,
            "num_reviews": 3,
            "playtime_forever": 487,
            "playtime_last_two_weeks": 487,
            "playtime_at_review": 164,
            "last_played": 1691781480
        },
        "language": "english",
        "review": "Devs : we wont continue pve but heres a few more gay heroes for you\n\nalso we put 2 on title so you need to pay money for that as well",
        "timestamp_created": 1691756625,
        "timestamp_updated": 1691756625,
        "voted_up": false,
        "votes_up": 2,
        "votes_funny": 0,
        "weighted_vote_score": "0.442917078733444214",
        "comment_count": 0,
        "steam_purchase": false,
        "received_for_free": false,
        "written_during_early_access": false,
        "hidden_in_steam_china": true,
        "steam_china_location": ""
    },
    {
        "recommendationid": "143881730",
        "author": {
            "steamid": "76561198319001955",
            "num_games_owned": 0,
            "num_reviews": 1,
            "playtime_forever": 82,
            "playtime_last_two_weeks": 82,
            "playtime_at_review": 82,
            "last_played": 1691725370
        },
        "language": "schinese",
        "review": "垃圾暴雪 喜欢自己锁是吧 网易怎么你了 还蹬鼻子上脸 活该 玩家是真喜欢这游戏 你们自己把自己整的人不像人狗不像狗的",
        "timestamp_created": 1691756624,
        "timestamp_updated": 1691756624,
        "voted_up": false,
        "votes_up": 0,
        "votes_funny": 1,
        "weighted_vote_score": 0,
        "comment_count": 0,
        "steam_purchase": false,
        "received_for_free": false,
        "written_during_early_access": false,
        "hidden_in_steam_china": true,
        "steam_china_location": ""
    },
    {
        "recommendationid": "143881728",
        "author": {
            "steamid": "76561198145747760",
            "num_games_owned": 0,
            "num_reviews": 37,
            "playtime_forever": 10,
            "playtime_last_two_weeks": 10,
            "playtime_at_review": 10,
            "last_played": 1691756597
        },
        "language": "schinese",
        "review": "曾经有多爱，现在有多恨。",
        "timestamp_created": 1691756623,
        "timestamp_updated": 1691756623,
        "voted_up": false,
        "votes_up": 0,
        "votes_funny": 0,
        "weighted_vote_score": 0,
        "comment_count": 0,
        "steam_purchase": false,
        "received_for_free": false,
        "written_during_early_access": false,
        "hidden_in_steam_china": true,
        "steam_china_location": ""
    },
    {
        "recommendationid": "143881725",
        "author": {
            "steamid": "76561198396827664",
            "num_games_owned": 0,
            "num_reviews": 2,
            "playtime_forever": 175,
            "playtime_last_two_weeks": 175,
            "playtime_at_review": 52,
            "last_played": 1691773208
        },
        "language": "spanish",
        "review": "Solo es divertido con amigos. Monetización, grindeo del pase de batalla, recompensas y hasta el nuevo modo historia (fraccionada en distintas paginas web y contenido del juego anterior inaccesible) todo horrible.",
        "timestamp_created": 1691756622,
        "timestamp_updated": 1691756622,
        "voted_up": false,
        "votes_up": 1,
        "votes_funny": 0,
        "weighted_vote_score": 0,
        "comment_count": 0,
        "steam_purchase": false,
        "received_for_free": false,
        "written_during_early_access": false,
        "hidden_in_steam_china": true,
        "steam_china_location": ""
    },
    {
        "recommendationid": "143881721",
        "author": {
            "steamid": "76561198852405793",
            "num_games_owned": 315,
            "num_reviews": 17,
            "playtime_forever": 11,
            "playtime_last_two_weeks": 11,
            "playtime_at_review": 11,
            "last_played": 1691756546
        },
        "language": "schinese",
        "review": "我浪费了十分钟时间，33g磁盘空间，身体与精神伤害，就是为了写这篇差评\n兄弟们，我做的对吗",
        "timestamp_created": 1691756620,
        "timestamp_updated": 1691756620,
        "voted_up": false,
        "votes_up": 0,
        "votes_funny": 0,
        "weighted_vote_score": 0,
        "comment_count": 0,
        "steam_purchase": false,
        "received_for_free": false,
        "written_during_early_access": false,
        "hidden_in_steam_china": true,
        "steam_china_location": ""
    },
    {
        "recommendationid": "143881720",
        "author": {
            "steamid": "76561198301903709",
            "num_games_owned": 95,
            "num_reviews": 6,
            "playtime_forever": 347,
            "playtime_last_two_weeks": 347,
            "playtime_at_review": 345,
            "last_played": 1691756750
        },
        "language": "schinese",
        "review": "给个差评舒服了。吃饭吃饭。76手感改的不错。但是不影响我差评。几百级的号，一堆活动皮金皮说没就没了。赶紧给爷噶。",
        "timestamp_created": 1691756620,
        "timestamp_updated": 1691756620,
        "voted_up": false,
        "votes_up": 0,
        "votes_funny": 0,
        "weighted_vote_score": 0,
        "comment_count": 0,
        "steam_purchase": false,
        "received_for_free": false,
        "written_during_early_access": false,
        "hidden_in_steam_china": true,
        "steam_china_location": ""
    },
    {
        "recommendationid": "143881716",
        "author": {
            "steamid": "76561198347298929",
            "num_games_owned": 172,
            "num_reviews": 16,
            "playtime_forever": 11,
            "playtime_last_two_weeks": 11,
            "playtime_at_review": 11,
            "last_played": 1691756459
        },
        "language": "schinese",
        "review": "原价买的游戏，前阵子变免费，我就不说啥了，起码还给点东西。上线之后给的那些东西我都有点要骂娘了。新英雄还没完多久呢。直接游戏都不给玩了？司马暴雪！趁早黄。",
        "timestamp_created": 1691756618,
        "timestamp_updated": 1691756618,
        "voted_up": false,
        "votes_up": 0,
        "votes_funny": 0,
        "weighted_vote_score": 0,
        "comment_count": 0,
        "steam_purchase": false,
        "received_for_free": false,
        "written_during_early_access": false,
        "hidden_in_steam_china": true,
        "steam_china_location": ""
    },
    {
        "recommendationid": "143881714",
        "author": {
            "steamid": "76561198028336141",
            "num_games_owned": 136,
            "num_reviews": 8,
            "playtime_forever": 216,
            "playtime_last_two_weeks": 216,
            "playtime_at_review": 95,
            "last_played": 1691780833
        },
        "language": "russian",
        "review": "Пиздатая игра, но пве не куплю =*",
        "timestamp_created": 1691756616,
        "timestamp_updated": 1691756616,
        "voted_up": true,
        "votes_up": 1,
        "votes_funny": 1,
        "weighted_vote_score": "0.523809552192687988",
        "comment_count": 1,
        "steam_purchase": false,
        "received_for_free": false,
        "written_during_early_access": false,
        "hidden_in_steam_china": true,
        "steam_china_location": ""
    },
    {
        "recommendationid": "143881711",
        "author": {
            "steamid": "76561198974913694",
            "num_games_owned": 83,
            "num_reviews": 1,
            "playtime_forever": 27,
            "playtime_last_two_weeks": 27,
            "playtime_at_review": 27,
            "last_played": 1691734703
        },
        "language": "schinese",
        "review": "看什么快点刷差评啊垃圾暴雪",
        "timestamp_created": 1691756613,
        "timestamp_updated": 1691756613,
        "voted_up": false,
        "votes_up": 0,
        "votes_funny": 0,
        "weighted_vote_score": 0,
        "comment_count": 0,
        "steam_purchase": false,
        "received_for_free": false,
        "written_during_early_access": false,
        "hidden_in_steam_china": true,
        "steam_china_location": ""
    },
    {
        "recommendationid": "143881710",
        "author": {
            "steamid": "76561198196341089",
            "num_games_owned": 170,
            "num_reviews": 23,
            "playtime_forever": 35,
            "playtime_last_two_weeks": 35,
            "playtime_at_review": 35,
            "last_played": 1691756443
        },
        "language": "english",
        "review": "They care more about money than the game.\nGimme back my 6v6 shooter!",
        "timestamp_created": 1691756612,
        "timestamp_updated": 1691756612,
        "voted_up": false,
        "votes_up": 0,
        "votes_funny": 0,
        "weighted_vote_score": 0,
        "comment_count": 0,
        "steam_purchase": false,
        "received_for_free": false,
        "written_during_early_access": false,
        "hidden_in_steam_china": true,
        "steam_china_location": ""
    },
    {
        "recommendationid": "143881709",
        "author": {
            "steamid": "76561198451930572",
            "num_games_owned": 93,
            "num_reviews": 2,
            "playtime_forever": 222,
            "playtime_last_two_weeks": 222,
            "playtime_at_review": 24,
            "last_played": 1691768410
        },
        "language": "schinese",
        "review": "游戏黑屏直接进不去 傻逼暴雪",
        "timestamp_created": 1691756611,
        "timestamp_updated": 1691756611,
        "voted_up": false,
        "votes_up": 0,
        "votes_funny": 0,
        "weighted_vote_score": 0,
        "comment_count": 0,
        "steam_purchase": false,
        "received_for_free": false,
        "written_during_early_access": false,
        "hidden_in_steam_china": true,
        "steam_china_location": ""
    },
    {
        "recommendationid": "143881708",
        "author": {
            "steamid": "76561198135409815",
            "num_games_owned": 0,
            "num_reviews": 1,
            "playtime_forever": 14,
            "playtime_last_two_weeks": 14,
            "playtime_at_review": 14,
            "last_played": 1691734305
        },
        "language": "schinese",
        "review": "——---————/´ ¯/)\n—— ———--/—-/\n— ————-/—-/\n———--/´¯/'--'/´¯`•_\n———-/'/--/—-/—--/¨¯\\\n——--('(———- ¯~/'--')\n— ——\\————-'—--/\n———-'\\'————_-•´\n— ———\\———--(\n—— ——-\\———-\u0018",
        "timestamp_created": 1691756610,
        "timestamp_updated": 1691756610,
        "voted_up": false,
        "votes_up": 0,
        "votes_funny": 0,
        "weighted_vote_score": 0,
        "comment_count": 0,
        "steam_purchase": false,
        "received_for_free": false,
        "written_during_early_access": false,
        "hidden_in_steam_china": true,
        "steam_china_location": ""
    },
    {
        "recommendationid": "143881707",
        "author": {
            "steamid": "76561199182571870",
            "num_games_owned": 0,
            "num_reviews": 1,
            "playtime_forever": 17,
            "playtime_last_two_weeks": 17,
            "playtime_at_review": 11,
            "last_played": 1691756821
        },
        "language": "schinese",
        "review": "我的六年青春是OW1\nOW2是什么垃圾游戏？\n暴雪是什么垃圾公司？",
        "timestamp_created": 1691756608,
        "timestamp_updated": 1691756608,
        "voted_up": false,
        "votes_up": 0,
        "votes_funny": 0,
        "weighted_vote_score": 0,
        "comment_count": 0,
        "steam_purchase": false,
        "received_for_free": false,
        "written_during_early_access": false,
        "hidden_in_steam_china": true,
        "steam_china_location": ""
    },
    {
        "recommendationid": "143881705",
        "author": {
            "steamid": "76561199123075342",
            "num_games_owned": 143,
            "num_reviews": 2,
            "playtime_forever": 7,
            "playtime_last_two_weeks": 7,
            "playtime_at_review": 7,
            "last_played": 1691756396
        },
        "language": "schinese",
        "review": "好si，滚",
        "timestamp_created": 1691756608,
        "timestamp_updated": 1691756608,
        "voted_up": false,
        "votes_up": 0,
        "votes_funny": 0,
        "weighted_vote_score": 0,
        "comment_count": 0,
        "steam_purchase": false,
        "received_for_free": false,
        "written_during_early_access": false,
        "hidden_in_steam_china": true,
        "steam_china_location": ""
    },
    {
        "recommendationid": "143881703",
        "author": {
            "steamid": "76561199467135493",
            "num_games_owned": 0,
            "num_reviews": 1,
            "playtime_forever": 538,
            "playtime_last_two_weeks": 538,
            "playtime_at_review": 538,
            "last_played": 1691745110
        },
        "language": "schinese",
        "review": "好玩，但是垃圾",
        "timestamp_created": 1691756607,
        "timestamp_updated": 1691756607,
        "voted_up": false,
        "votes_up": 0,
        "votes_funny": 0,
        "weighted_vote_score": 0,
        "comment_count": 0,
        "steam_purchase": false,
        "received_for_free": false,
        "written_during_early_access": false,
        "hidden_in_steam_china": true,
        "steam_china_location": ""
    },
    {
        "recommendationid": "143881701",
        "author": {
            "steamid": "76561198850892121",
            "num_games_owned": 269,
            "num_reviews": 8,
            "playtime_forever": 471,
            "playtime_last_two_weeks": 471,
            "playtime_at_review": 77,
            "last_played": 1691780265
        },
        "language": "russian",
        "review": "как истинный фанат овервотча, я поставлю негативный отзыв \n",
        "timestamp_created": 1691756606,
        "timestamp_updated": 1691756606,
        "voted_up": false,
        "votes_up": 0,
        "votes_funny": 0,
        "weighted_vote_score": 0,
        "comment_count": 0,
        "steam_purchase": false,
        "received_for_free": false,
        "written_during_early_access": false,
        "hidden_in_steam_china": true,
        "steam_china_location": ""
    },
    {
        "recommendationid": "143881700",
        "author": {
            "steamid": "76561198841687440",
            "num_games_owned": 0,
            "num_reviews": 3,
            "playtime_forever": 116,
            "playtime_last_two_weeks": 116,
            "playtime_at_review": 116,
            "last_played": 1691748324
        },
        "language": "schinese",
        "review": "守望先锋是个好游戏，守望先锋2和鲍勃尻迪克不是好东西！",
        "timestamp_created": 1691756605,
        "timestamp_updated": 1691756605,
        "voted_up": false,
        "votes_up": 0,
        "votes_funny": 0,
        "weighted_vote_score": 0,
        "comment_count": 0,
        "steam_purchase": false,
        "received_for_free": false,
        "written_during_early_access": false,
        "hidden_in_steam_china": true,
        "steam_china_location": ""
    },
    {
        "recommendationid": "143881699",
        "author": {
            "steamid": "76561198391352730",
            "num_games_owned": 0,
            "num_reviews": 2,
            "playtime_forever": 8,
            "playtime_last_two_weeks": 8,
            "playtime_at_review": 8,
            "last_played": 1691756506
        },
        "language": "schinese",
        "review": "需要战网通行证登入游戏，真的很麻烦，还没有搞定的还是不要下载了。",
        "timestamp_created": 1691756604,
        "timestamp_updated": 1691756604,
        "voted_up": false,
        "votes_up": 0,
        "votes_funny": 0,
        "weighted_vote_score": 0,
        "comment_count": 0,
        "steam_purchase": false,
        "received_for_free": false,
        "written_during_early_access": false,
        "hidden_in_steam_china": true,
        "steam_china_location": ""
    },
    {
        "recommendationid": "143881698",
        "author": {
            "steamid": "76561198980646771",
            "num_games_owned": 25,
            "num_reviews": 3,
            "playtime_forever": 184,
            "playtime_last_two_weeks": 184,
            "playtime_at_review": 184,
            "last_played": 1691756241
        },
        "language": "schinese",
        "review": "傻逼暴雪我操你妈傻逼暴雪我操你妈傻逼暴雪我操你妈傻逼暴雪我操你妈傻逼暴雪我操你妈傻逼暴雪我操你妈傻逼暴雪我操你妈傻逼暴雪我操你妈傻逼暴雪我操你妈傻逼暴雪我操你妈傻逼暴雪我操你妈傻逼暴雪我操你妈傻逼暴雪我操你妈傻逼暴雪我操你妈傻逼暴雪我操你妈傻逼暴雪我操你妈傻逼暴雪我操你妈傻逼暴雪我操你妈傻逼暴雪我操你妈傻逼暴雪我操你妈傻逼暴雪我操你妈傻逼暴雪我操你妈傻逼暴雪我操你妈傻逼暴雪我操你妈傻逼暴雪我操你妈傻逼暴雪我操你妈傻逼暴雪我操你妈傻逼暴雪我操你妈傻逼暴雪我操你妈傻逼暴雪我操你妈傻逼暴雪我操你妈傻逼暴雪我操你妈傻逼暴雪我操你妈傻逼暴雪我操你妈傻逼暴雪我操你妈傻逼暴雪我操你妈傻逼暴雪我操你妈傻逼暴雪我操你妈傻逼暴雪我操你妈傻逼暴雪我操你妈傻逼暴雪我操你妈傻逼暴雪我操你妈傻逼暴雪我操你妈傻逼暴雪我操你妈傻逼暴雪我操你妈傻逼暴雪我操你妈傻逼暴雪我操你妈傻逼暴雪我操你妈傻逼暴雪我操你妈傻逼暴雪我操你妈傻逼暴雪我操你妈傻逼暴雪我操你妈傻逼暴雪我操你妈傻逼暴雪我操你妈傻逼暴雪我操你妈傻逼暴雪我操你妈傻逼暴雪我操你妈傻逼暴雪我操你妈傻逼暴雪我操你妈傻逼暴雪我操你妈傻逼暴雪我操你妈傻逼暴雪我操你妈傻逼暴雪我操你妈傻逼暴雪我操你妈傻逼暴雪我操你妈傻逼暴雪我操你妈傻逼暴雪我操你妈傻逼暴雪我操你妈傻逼暴雪我操你妈傻逼暴雪我操你妈傻逼暴雪我操你妈傻逼暴雪我操你妈傻逼暴雪我操你妈傻逼暴雪我操你妈傻逼暴雪我操你妈傻逼暴雪我操你妈傻逼暴雪我操你妈傻逼暴雪我操你妈傻逼暴雪我操你妈傻逼暴雪我操你妈傻逼暴雪我操你妈傻逼暴雪我操你妈傻逼暴雪我操你妈傻逼暴雪我操你妈傻逼暴雪我操你妈傻逼暴雪我操你妈傻逼暴雪我操你妈傻逼暴雪我操你妈傻逼暴雪我操你妈傻逼暴雪我操你妈傻逼暴雪我操你妈傻逼暴雪我操你妈傻逼暴雪我操你妈傻逼暴雪我操你妈傻逼暴雪我操你妈傻逼暴雪我操你妈傻逼暴雪我操你妈傻逼暴雪我操你妈傻逼暴雪我操你妈傻逼暴雪我操你妈傻逼暴雪我操你妈傻逼暴雪我操你妈傻逼暴雪我操你妈傻逼暴雪我操你妈傻逼暴雪我操你妈傻逼暴雪我操你妈傻逼暴雪我操你妈傻逼暴雪我操你妈傻逼暴雪我操你妈傻逼暴雪我操你妈傻逼暴雪我操你妈傻逼暴雪我操你妈傻逼暴雪我操你妈傻逼暴雪我操你妈傻逼暴雪我操你妈傻逼暴雪我操你妈傻逼暴雪我操你妈傻逼暴雪我操你妈傻逼暴雪我操你妈傻逼暴雪我操你妈傻逼暴雪我操你妈傻逼暴雪我操你妈傻逼暴雪我操你妈傻逼暴雪我操你妈傻逼暴雪我操你妈傻逼暴雪我操你妈傻逼暴雪我操你妈傻逼暴雪我操你妈傻逼暴雪我操你妈傻逼暴雪我操你妈傻逼暴雪我操你妈傻逼暴雪我操你妈傻逼暴雪我操你妈傻逼暴雪我操你妈傻逼暴雪我操你妈傻逼暴雪我操你妈傻逼暴雪我操你妈傻逼暴雪我操你妈傻逼暴雪我操你妈傻逼暴雪我操你妈傻逼暴雪我操你妈傻逼暴雪我操你妈傻逼暴雪我操你妈傻逼暴雪我操你妈傻逼暴雪我操你妈傻逼暴雪我操你妈傻逼暴雪我操你妈傻逼暴雪我操你妈傻逼暴雪我操你妈傻逼暴雪我操你妈傻逼暴雪我操你妈傻逼暴雪我操你妈傻逼暴雪我操你妈傻逼暴雪我操你妈傻逼暴雪我操你妈傻逼暴雪我操你妈傻逼暴雪我操你妈傻逼暴雪我操你妈傻逼暴雪我操你妈傻逼暴雪我操你妈傻逼暴雪我操你妈傻逼暴雪我操你妈傻逼暴雪我操你妈傻逼暴雪我操你妈傻逼暴雪我操你妈傻逼暴雪我操你妈傻逼暴雪我操你妈傻逼暴雪我操你妈傻逼暴雪我操你妈傻逼暴雪我操你妈傻逼暴雪我操你妈傻逼暴雪我操你妈傻逼暴雪我操你妈傻逼暴雪我操你妈傻逼暴雪我操你妈傻逼暴雪我操你妈傻逼暴雪我操你妈傻逼暴雪我操你妈傻逼暴雪我操你妈傻逼暴雪我操你妈傻逼暴雪我操你妈傻逼暴雪我操你妈傻逼暴雪我操你妈傻逼暴雪我操你妈傻逼暴雪我操你妈傻逼暴雪我操你妈傻逼暴雪我操你妈傻逼暴雪我操你妈傻逼暴雪我操你妈傻逼暴雪我操你妈傻逼暴雪我操你妈傻逼暴雪我操你妈傻逼暴雪我操你妈傻逼暴雪我操你妈傻逼暴雪我操你妈傻逼暴雪我操你妈傻逼暴雪我操你妈傻逼暴雪我操你妈傻逼暴雪我操你妈傻逼暴雪我操你妈傻逼暴雪我操你妈傻逼暴雪我操你妈傻逼暴雪我操你妈傻逼暴雪我操你妈傻逼暴雪我操你妈傻逼暴雪我操你妈傻逼暴雪我操你妈傻逼暴雪我操你妈傻逼暴雪我操你妈傻逼暴雪我操你妈傻逼暴雪我操你妈傻逼暴雪我操你妈傻逼暴雪我操你妈傻逼暴雪我操你妈傻逼暴雪我操你妈傻逼暴雪我操你妈傻逼暴雪我操你妈傻逼暴雪我操你妈傻逼暴雪我操你妈傻逼暴雪我操你妈傻逼暴雪我操你妈傻逼暴雪我操你妈傻逼暴雪我操你妈傻逼暴雪我操你妈傻逼暴雪我操你妈傻逼暴雪我操你妈傻逼暴雪我操你妈傻逼暴雪我操你妈傻逼暴雪我操你妈傻逼暴雪我操你妈傻逼暴雪我操你妈傻逼暴雪我操你妈傻逼暴雪我操你妈傻逼暴雪我操你妈傻逼暴雪我操你妈傻逼暴雪我操你妈傻逼暴雪我操你妈傻逼暴雪我操你妈傻逼暴雪我操你妈傻逼暴雪我操你妈傻逼暴雪我操你妈傻逼暴雪我操你妈傻逼暴雪我操你妈傻逼暴雪我操你妈傻逼暴雪我操你妈傻逼暴雪我操你妈傻逼暴雪我操你妈傻逼暴雪我操你妈傻逼暴雪我操你妈傻逼暴雪我操你妈傻逼暴雪我操你妈傻逼暴雪我操你妈傻逼暴雪我操你妈傻逼暴雪我操你妈傻逼暴雪我操你妈傻逼暴雪我操你妈傻逼暴雪我操你妈傻逼暴雪我操你妈傻逼暴雪我操你妈傻逼暴雪我操你妈傻逼暴雪我操你妈傻逼暴雪我操你妈傻逼暴雪我操你妈傻逼暴雪我操你妈傻逼暴雪我操你妈傻逼暴雪我操你妈傻逼暴雪我操你妈傻逼暴雪我操你妈傻逼暴雪我操你妈傻逼暴雪我操你妈傻逼暴雪我操你妈傻逼暴雪我操你妈傻逼暴雪我操你妈傻逼暴雪我操你妈傻逼暴雪我操你妈傻逼暴雪我操你妈傻逼暴雪我操你妈傻逼暴雪我操你妈傻逼暴雪我操你妈傻逼暴雪我操你妈傻逼暴雪我操你妈傻逼暴雪我操你妈傻逼暴雪我操你妈傻逼暴雪我操你妈傻逼暴雪我操你妈傻逼暴雪我操你妈傻逼暴雪我操你妈傻逼暴雪我操你妈傻逼暴雪我操你妈傻逼暴雪我操你妈傻逼暴雪我操你妈傻逼暴雪我操你妈傻逼暴雪我操你妈傻逼暴雪我操你妈傻逼暴雪我操你妈傻逼暴雪我操你妈傻逼暴雪我操你妈傻逼暴雪我操你妈傻逼暴雪我操你妈傻逼暴雪我操你妈傻逼暴雪我操你妈傻逼暴雪我操你妈傻逼暴雪我操你妈傻逼暴雪我操你妈傻逼暴雪我操你妈傻逼暴雪我操你妈傻逼暴雪我操你妈傻逼暴雪我操你妈傻逼暴雪我操你妈傻逼暴雪我操你妈傻逼暴雪我操你妈傻逼暴雪我操你妈傻逼暴雪我操你妈傻逼暴雪我操你妈傻逼暴雪我操你妈傻逼暴雪我操你妈傻逼暴雪我操你妈傻逼暴雪我操你妈傻逼暴雪我操你妈傻逼暴雪我操你妈傻逼暴雪我操你妈傻逼暴雪我操你妈傻逼暴雪我操你妈傻逼暴雪我操你妈傻逼暴雪我操你妈傻逼暴雪我操你妈傻逼暴雪我操你妈傻逼暴雪我操你妈傻逼暴雪我操你妈傻逼暴雪我操你妈傻逼暴雪我操你妈傻逼暴雪我操你妈傻逼暴雪我操你妈傻逼暴雪我操你妈傻逼暴雪我操你妈傻逼暴雪我操你妈傻逼暴雪我操你妈傻逼暴雪我操你妈傻逼暴雪我操你妈傻逼暴雪我操你妈傻逼暴雪我操你妈傻逼暴雪我操你妈傻逼暴雪我操你妈傻逼暴雪我操你妈傻逼暴雪我操你妈傻逼暴雪我操你妈傻逼暴雪我操你妈傻逼暴雪我操你妈傻逼暴雪我操你妈傻逼暴雪我操你妈傻逼暴雪我操你妈傻逼暴雪我操你妈傻逼暴雪我操你妈傻逼暴雪我操你妈傻逼暴雪我操你妈傻逼暴雪我操你妈傻逼暴雪我操你妈傻逼暴雪我操你妈傻逼暴雪我操你妈傻逼暴雪我操你妈傻逼暴雪我操你妈傻逼暴雪我操你妈傻逼暴雪我操你妈傻逼暴雪我操你妈傻逼暴雪我操你妈傻逼暴雪我操你妈傻逼暴雪我操你妈傻逼暴雪我操你妈傻逼暴雪我操你妈傻逼暴雪我操你妈傻逼暴雪我操你妈傻逼暴雪我操你妈傻逼暴雪我操你妈傻逼暴雪我操你妈傻逼暴雪我操你妈傻逼暴雪我操你妈傻逼暴雪我操你妈傻逼暴雪我操你妈傻逼暴雪我操你妈傻逼暴雪我操你妈傻逼暴雪我操你妈傻逼暴雪我操你妈傻逼暴雪我操你妈傻逼暴雪我操你妈傻逼暴雪我操你妈傻逼暴雪我操你妈傻逼暴雪我操你妈傻逼暴雪我操你妈傻逼暴雪我操你妈傻逼暴雪我操你妈傻逼暴雪我操你妈傻逼暴雪我操你妈",
        "timestamp_created": 1691756604,
        "timestamp_updated": 1691756604,
        "voted_up": false,
        "votes_up": 0,
        "votes_funny": 0,
        "weighted_vote_score": 0,
        "comment_count": 0,
        "steam_purchase": false,
        "received_for_free": false,
        "written_during_early_access": false,
        "hidden_in_steam_china": true,
        "steam_china_location": ""
    },
    {
        "recommendationid": "143881697",
        "author": {
            "steamid": "76561198290357902",
            "num_games_owned": 220,
            "num_reviews": 10,
            "playtime_forever": 141,
            "playtime_last_two_weeks": 141,
            "playtime_at_review": 14,
            "last_played": 1691770128
        },
        "language": "schinese",
        "review": "暴雪司马",
        "timestamp_created": 1691756603,
        "timestamp_updated": 1691756603,
        "voted_up": false,
        "votes_up": 1,
        "votes_funny": 0,
        "weighted_vote_score": "0.519999980926513672",
        "comment_count": 0,
        "steam_purchase": false,
        "received_for_free": false,
        "written_during_early_access": false,
        "hidden_in_steam_china": true,
        "steam_china_location": ""
    },
    {
        "recommendationid": "143881695",
        "author": {
            "steamid": "76561198837705739",
            "num_games_owned": 0,
            "num_reviews": 1,
            "playtime_forever": 16,
            "playtime_last_two_weeks": 16,
            "playtime_at_review": 16,
            "last_played": 1691756537
        },
        "language": "koreana",
        "review": "They took away OW1 and forced an orders of magnitude more predatory MTX. No compensation for people who payed full price for a game they can no longer play.",
        "timestamp_created": 1691756601,
        "timestamp_updated": 1691756601,
        "voted_up": false,
        "votes_up": 0,
        "votes_funny": 0,
        "weighted_vote_score": 0,
        "comment_count": 0,
        "steam_purchase": false,
        "received_for_free": false,
        "written_during_early_access": false,
        "hidden_in_steam_china": true,
        "steam_china_location": ""
    },
    {
        "recommendationid": "143881692",
        "author": {
            "steamid": "76561198874483475",
            "num_games_owned": 35,
            "num_reviews": 1,
            "playtime_forever": 27,
            "playtime_last_two_weeks": 27,
            "playtime_at_review": 25,
            "last_played": 1691773396
        },
        "language": "schinese",
        "review": "飒比的暴雪",
        "timestamp_created": 1691756599,
        "timestamp_updated": 1691756599,
        "voted_up": false,
        "votes_up": 0,
        "votes_funny": 0,
        "weighted_vote_score": 0,
        "comment_count": 0,
        "steam_purchase": false,
        "received_for_free": false,
        "written_during_early_access": false,
        "hidden_in_steam_china": true,
        "steam_china_location": ""
    },
    {
        "recommendationid": "143881691",
        "author": {
            "steamid": "76561198174773457",
            "num_games_owned": 0,
            "num_reviews": 1,
            "playtime_forever": 327,
            "playtime_last_two_weeks": 327,
            "playtime_at_review": 96,
            "last_played": 1691776891
        },
        "language": "schinese",
        "review": "沙比暴雪，沙比考迪克！点赞一次烤考迪克的迪克！",
        "timestamp_created": 1691756598,
        "timestamp_updated": 1691756598,
        "voted_up": false,
        "votes_up": 0,
        "votes_funny": 0,
        "weighted_vote_score": 0,
        "comment_count": 0,
        "steam_purchase": false,
        "received_for_free": false,
        "written_during_early_access": false,
        "hidden_in_steam_china": true,
        "steam_china_location": ""
    },
    {
        "recommendationid": "143881689",
        "author": {
            "steamid": "76561199075859946",
            "num_games_owned": 0,
            "num_reviews": 1,
            "playtime_forever": 217,
            "playtime_last_two_weeks": 217,
            "playtime_at_review": 108,
            "last_played": 1691771521
        },
        "language": "schinese",
        "review": "勾 矢",
        "timestamp_created": 1691756597,
        "timestamp_updated": 1691756597,
        "voted_up": false,
        "votes_up": 0,
        "votes_funny": 0,
        "weighted_vote_score": 0,
        "comment_count": 0,
        "steam_purchase": false,
        "received_for_free": false,
        "written_during_early_access": false,
        "hidden_in_steam_china": true,
        "steam_china_location": ""
    },
    {
        "recommendationid": "143881687",
        "author": {
            "steamid": "76561198810793044",
            "num_games_owned": 0,
            "num_reviews": 2,
            "playtime_forever": 341,
            "playtime_last_two_weeks": 341,
            "playtime_at_review": 62,
            "last_played": 1691772110
        },
        "language": "schinese",
        "review": "贱婢游戏贱婢总裁",
        "timestamp_created": 1691756594,
        "timestamp_updated": 1691756594,
        "voted_up": false,
        "votes_up": 0,
        "votes_funny": 0,
        "weighted_vote_score": 0,
        "comment_count": 0,
        "steam_purchase": false,
        "received_for_free": false,
        "written_during_early_access": false,
        "hidden_in_steam_china": true,
        "steam_china_location": ""
    },
    {
        "recommendationid": "143881680",
        "author": {
            "steamid": "76561198335703457",
            "num_games_owned": 492,
            "num_reviews": 17,
            "playtime_forever": 219,
            "playtime_last_two_weeks": 219,
            "playtime_at_review": 91,
            "last_played": 1691769043
        },
        "language": "schinese",
        "review": "守望先锋天下第一",
        "timestamp_created": 1691756590,
        "timestamp_updated": 1691756590,
        "voted_up": false,
        "votes_up": 0,
        "votes_funny": 0,
        "weighted_vote_score": 0,
        "comment_count": 0,
        "steam_purchase": false,
        "received_for_free": false,
        "written_during_early_access": false,
        "hidden_in_steam_china": true,
        "steam_china_location": ""
    },
    {
        "recommendationid": "143881679",
        "author": {
            "steamid": "76561198134588905",
            "num_games_owned": 93,
            "num_reviews": 8,
            "playtime_forever": 7,
            "playtime_last_two_weeks": 7,
            "playtime_at_review": 7,
            "last_played": 1691756463
        },
        "language": "schinese",
        "review": "我下载了，请问考迪克的妈妈去哪里艹",
        "timestamp_created": 1691756590,
        "timestamp_updated": 1691756590,
        "voted_up": false,
        "votes_up": 0,
        "votes_funny": 0,
        "weighted_vote_score": 0,
        "comment_count": 0,
        "steam_purchase": false,
        "received_for_free": false,
        "written_during_early_access": false,
        "hidden_in_steam_china": true,
        "steam_china_location": ""
    },
    {
        "recommendationid": "143881678",
        "author": {
            "steamid": "76561199122239624",
            "num_games_owned": 35,
            "num_reviews": 3,
            "playtime_forever": 177,
            "playtime_last_two_weeks": 177,
            "playtime_at_review": 177,
            "last_played": 1691743018
        },
        "language": "schinese",
        "review": "暴雪我操你妈暴雪我操你妈暴雪我操你妈暴雪我操你妈暴雪我操你妈暴雪我操你妈暴雪我操你妈暴雪我操你妈暴雪我操你妈暴雪我操你妈暴雪我操你妈暴雪我操你妈暴雪我操你妈暴雪我操你妈暴雪我操你妈暴雪我操你妈还我国服那么多金皮还我国服那么多金皮还我国服那么多金皮还我国服那么多金皮还我国服那么多金皮还我国服那么多金皮还我国服那么多金皮还我国服那么多金皮还我国服那么多金皮还我国服那么多金皮还我国服那么多金皮还我国服那么多金皮还我国服那么多金皮还我国服那么多金皮还我国服那么多金皮你个几把玩意我操你妈你个几把玩意我操你妈你个几把玩意我操你妈你个几把玩意我操你妈你个几把玩意我操你妈你个几把玩意我操你妈你个几把玩意我操你妈你个几把玩意我操你妈你个几把玩意我操你妈你个几把玩意我操你妈你个几把玩意我操你妈你个几把玩意我操你妈你个几把玩意我操你妈你个几把玩意我操你妈你个几把玩意我操你妈你个几把玩意我操你妈你个几把玩意我操你妈你个几把玩意我操你妈你个几把玩意我操你妈你个几把玩意我操你妈你个几把玩意我操你妈你个几把玩意我操你妈你个几把玩意我操你妈你个几把玩意我操你妈你个几把玩意我操你妈你个几把玩意我操你妈你个几把玩意我操你妈你个几把玩意我操你妈\n\nBlizzard I fuck your mother blizzard I fuck your mother blizzard I fuck your mother blizzard I fuck your mother blizzard I fuck your mother blizzard I fuck your mother blizzard I fuck your mother blizzard I fuck your mother blizzard I fuck your mother blizzard I fuck your mother I fuck your mother blizzard I also take so much gold and so much gold and so much gold There are so many gold and so many gold and so many gold and so many gold and so many gold and so many gold and so many gold and so many gold and so many gold and so many gold and so many gold and so many gold and so many gold and so many gold and so many gold and so many gold and so many things I fuck you You know what? I'm gonna fuck you, I'm gonna fuck you, I'm gonna fuck you, I'm gonna fuck you, I'm gonna fuck you, I'm gonna fuck you, I'm gonna fuck you, I'm gonna fuck you You know what? I'm gonna fuck you, I'm gonna fuck you, I'm gonna fuck you, I'm gonna fuck you, I'm gonna fuck you, I'm gonna fuck you, I'm gonna fuck you, I'm gonna fuck you Fuck you, fuck you, fuck you, fuck you, fuck you, fuck you",
        "timestamp_created": 1691756590,
        "timestamp_updated": 1691756590,
        "voted_up": false,
        "votes_up": 0,
        "votes_funny": 0,
        "weighted_vote_score": 0,
        "comment_count": 0,
        "steam_purchase": false,
        "received_for_free": false,
        "written_during_early_access": false,
        "hidden_in_steam_china": true,
        "steam_china_location": ""
    },
    {
        "recommendationid": "143881676",
        "author": {
            "steamid": "76561198053595129",
            "num_games_owned": 27,
            "num_reviews": 2,
            "playtime_forever": 55,
            "playtime_last_two_weeks": 55,
            "playtime_at_review": 5,
            "last_played": 1691767907
        },
        "language": "schinese",
        "review": "好游戏 来steam又多了个地方可以给差评了",
        "timestamp_created": 1691756589,
        "timestamp_updated": 1691756589,
        "voted_up": false,
        "votes_up": 0,
        "votes_funny": 0,
        "weighted_vote_score": 0,
        "comment_count": 0,
        "steam_purchase": false,
        "received_for_free": false,
        "written_during_early_access": false,
        "hidden_in_steam_china": true,
        "steam_china_location": ""
    },
    {
        "recommendationid": "143881673",
        "author": {
            "steamid": "76561199245301280",
            "num_games_owned": 31,
            "num_reviews": 1,
            "playtime_forever": 25,
            "playtime_last_two_weeks": 25,
            "playtime_at_review": 25,
            "last_played": 1691756525
        },
        "language": "schinese",
        "review": "不差评我就给三国杀好评",
        "timestamp_created": 1691756587,
        "timestamp_updated": 1691756587,
        "voted_up": false,
        "votes_up": 0,
        "votes_funny": 0,
        "weighted_vote_score": 0,
        "comment_count": 0,
        "steam_purchase": false,
        "received_for_free": false,
        "written_during_early_access": false,
        "hidden_in_steam_china": true,
        "steam_china_location": ""
    },
    {
        "recommendationid": "143881671",
        "author": {
            "steamid": "76561198417543787",
            "num_games_owned": 123,
            "num_reviews": 3,
            "playtime_forever": 9,
            "playtime_last_two_weeks": 9,
            "playtime_at_review": 9,
            "last_played": 1691756510
        },
        "language": "schinese",
        "review": "暴雪我草丝你的亲妈",
        "timestamp_created": 1691756585,
        "timestamp_updated": 1691756585,
        "voted_up": false,
        "votes_up": 1,
        "votes_funny": 0,
        "weighted_vote_score": "0.523809552192687988",
        "comment_count": 0,
        "steam_purchase": false,
        "received_for_free": false,
        "written_during_early_access": false,
        "hidden_in_steam_china": true,
        "steam_china_location": ""
    },
    {
        "recommendationid": "143881669",
        "author": {
            "steamid": "76561198827272159",
            "num_games_owned": 113,
            "num_reviews": 4,
            "playtime_forever": 245,
            "playtime_last_two_weeks": 245,
            "playtime_at_review": 199,
            "last_played": 1691764272
        },
        "language": "schinese",
        "review": "第一次玩 挺好玩的 差评",
        "timestamp_created": 1691756585,
        "timestamp_updated": 1691756585,
        "voted_up": false,
        "votes_up": 0,
        "votes_funny": 0,
        "weighted_vote_score": 0,
        "comment_count": 0,
        "steam_purchase": false,
        "received_for_free": false,
        "written_during_early_access": false,
        "hidden_in_steam_china": true,
        "steam_china_location": ""
    },
    {
        "recommendationid": "143881668",
        "author": {
            "steamid": "76561198814264750",
            "num_games_owned": 0,
            "num_reviews": 1,
            "playtime_forever": 13,
            "playtime_last_two_weeks": 13,
            "playtime_at_review": 13,
            "last_played": 1691756522
        },
        "language": "schinese",
        "review": "感谢评论区的好兄弟指引怎么不下载就差评",
        "timestamp_created": 1691756584,
        "timestamp_updated": 1691756584,
        "voted_up": false,
        "votes_up": 0,
        "votes_funny": 0,
        "weighted_vote_score": 0,
        "comment_count": 0,
        "steam_purchase": false,
        "received_for_free": false,
        "written_during_early_access": false,
        "hidden_in_steam_china": true,
        "steam_china_location": ""
    },
    {
        "recommendationid": "143881667",
        "author": {
            "steamid": "76561199238554107",
            "num_games_owned": 16,
            "num_reviews": 1,
            "playtime_forever": 33,
            "playtime_last_two_weeks": 33,
            "playtime_at_review": 33,
            "last_played": 1691756480
        },
        "language": "schinese",
        "review": "游戏是个好游戏，但是傻逼暴雪，傻逼鲍勃考迪克，各位想要回去玩的，温馨提示，现在大多数英雄需要做任务才能解锁，你也可以直接付费购买：）   再次提醒，傻逼暴雪 傻逼鲍勃考迪克\n",
        "timestamp_created": 1691756583,
        "timestamp_updated": 1691756583,
        "voted_up": false,
        "votes_up": 0,
        "votes_funny": 0,
        "weighted_vote_score": 0,
        "comment_count": 0,
        "steam_purchase": false,
        "received_for_free": true,
        "written_during_early_access": false,
        "hidden_in_steam_china": true,
        "steam_china_location": ""
    },
    {
        "recommendationid": "143881658",
        "author": {
            "steamid": "76561198440923188",
            "num_games_owned": 0,
            "num_reviews": 7,
            "playtime_forever": 15,
            "playtime_last_two_weeks": 15,
            "playtime_at_review": 15,
            "last_played": 1691755078
        },
        "language": "schinese",
        "review": "暴雪我囸牛魔酬宾，透明度与国服号不共通,重新创号我开加速器都打不开",
        "timestamp_created": 1691756577,
        "timestamp_updated": 1691756577,
        "voted_up": false,
        "votes_up": 0,
        "votes_funny": 0,
        "weighted_vote_score": 0,
        "comment_count": 0,
        "steam_purchase": false,
        "received_for_free": false,
        "written_during_early_access": false,
        "hidden_in_steam_china": true,
        "steam_china_location": ""
    },
    {
        "recommendationid": "143881656",
        "author": {
            "steamid": "76561198336124383",
            "num_games_owned": 0,
            "num_reviews": 1,
            "playtime_forever": 22,
            "playtime_last_two_weeks": 22,
            "playtime_at_review": 22,
            "last_played": 1691756289
        },
        "language": "schinese",
        "review": "不管玩不玩，先吗你狗曰的暴雪再说",
        "timestamp_created": 1691756576,
        "timestamp_updated": 1691756576,
        "voted_up": false,
        "votes_up": 0,
        "votes_funny": 0,
        "weighted_vote_score": 0,
        "comment_count": 0,
        "steam_purchase": false,
        "received_for_free": false,
        "written_during_early_access": false,
        "hidden_in_steam_china": true,
        "steam_china_location": ""
    },
    {
        "recommendationid": "143881655",
        "author": {
            "steamid": "76561198388257299",
            "num_games_owned": 36,
            "num_reviews": 2,
            "playtime_forever": 203,
            "playtime_last_two_weeks": 203,
            "playtime_at_review": 80,
            "last_played": 1691763445
        },
        "language": "schinese",
        "review": "垃圾游戏，还敢上线玩你妈的丑批，日内瓦的退我钱",
        "timestamp_created": 1691756574,
        "timestamp_updated": 1691756574,
        "voted_up": false,
        "votes_up": 0,
        "votes_funny": 0,
        "weighted_vote_score": 0,
        "comment_count": 0,
        "steam_purchase": false,
        "received_for_free": false,
        "written_during_early_access": false,
        "hidden_in_steam_china": true,
        "steam_china_location": ""
    },
    {
        "recommendationid": "143881654",
        "author": {
            "steamid": "76561198243462266",
            "num_games_owned": 0,
            "num_reviews": 21,
            "playtime_forever": 7,
            "playtime_last_two_weeks": 7,
            "playtime_at_review": 7,
            "last_played": 1691756347
        },
        "language": "schinese",
        "review": "看到我的游戏时间了吗👆↑，它的长度曾代表了我的大学青春，现在却短得只为了写这句差评",
        "timestamp_created": 1691756574,
        "timestamp_updated": 1691756574,
        "voted_up": false,
        "votes_up": 0,
        "votes_funny": 0,
        "weighted_vote_score": 0,
        "comment_count": 0,
        "steam_purchase": false,
        "received_for_free": false,
        "written_during_early_access": false,
        "hidden_in_steam_china": true,
        "steam_china_location": ""
    },
    {
        "recommendationid": "143881652",
        "author": {
            "steamid": "76561198357553262",
            "num_games_owned": 63,
            "num_reviews": 2,
            "playtime_forever": 12,
            "playtime_last_two_weeks": 12,
            "playtime_at_review": 12,
            "last_played": 1691756356
        },
        "language": "schinese",
        "review": "一盘菜第一次出炉是香的\n第二次翻炒老顾客也觉得还行\n第三次再炒我们也忍住了\n第四次你还要往里添点屎告诉我们这是新菜然后大肆宣传圈钱然后关国服\n第五次你已经没有诚意的来告诉我这是一盘菜我也不会有心再陪你了大便要待在大便的位置",
        "timestamp_created": 1691756574,
        "timestamp_updated": 1691756574,
        "voted_up": false,
        "votes_up": 0,
        "votes_funny": 0,
        "weighted_vote_score": 0,
        "comment_count": 0,
        "steam_purchase": false,
        "received_for_free": false,
        "written_during_early_access": false,
        "hidden_in_steam_china": true,
        "steam_china_location": ""
    },
    {
        "recommendationid": "143881651",
        "author": {
            "steamid": "76561199111061541",
            "num_games_owned": 0,
            "num_reviews": 1,
            "playtime_forever": 6,
            "playtime_last_two_weeks": 6,
            "playtime_at_review": 6,
            "last_played": 1691756160
        },
        "language": "schinese",
        "review": "游戏是的好，曾经的暴雪也是好的，但现在只能说烤迪克是彼阳的晚易，初升的东曦，霞间的绯雾，似暮的篝壁",
        "timestamp_created": 1691756573,
        "timestamp_updated": 1691756573,
        "voted_up": false,
        "votes_up": 0,
        "votes_funny": 0,
        "weighted_vote_score": 0,
        "comment_count": 0,
        "steam_purchase": false,
        "received_for_free": false,
        "written_during_early_access": false,
        "hidden_in_steam_china": true,
        "steam_china_location": ""
    },
    {
        "recommendationid": "143881647",
        "author": {
            "steamid": "76561199404155506",
            "num_games_owned": 57,
            "num_reviews": 1,
            "playtime_forever": 181,
            "playtime_last_two_weeks": 181,
            "playtime_at_review": 149,
            "last_played": 1691761937
        },
        "language": "schinese",
        "review": "超越三国杀",
        "timestamp_created": 1691756569,
        "timestamp_updated": 1691756569,
        "voted_up": false,
        "votes_up": 0,
        "votes_funny": 0,
        "weighted_vote_score": 0,
        "comment_count": 0,
        "steam_purchase": false,
        "received_for_free": false,
        "written_during_early_access": false,
        "hidden_in_steam_china": true,
        "steam_china_location": ""
    },
    {
        "recommendationid": "143881646",
        "author": {
            "steamid": "76561198829838954",
            "num_games_owned": 0,
            "num_reviews": 1,
            "playtime_forever": 19,
            "playtime_last_two_weeks": 19,
            "playtime_at_review": 19,
            "last_played": 1691739631
        },
        "language": "schinese",
        "review": "大家的差评不要太保守啊，我们并不是说游戏多差，只是他不配拥有好评",
        "timestamp_created": 1691756568,
        "timestamp_updated": 1691756568,
        "voted_up": false,
        "votes_up": 0,
        "votes_funny": 0,
        "weighted_vote_score": 0,
        "comment_count": 0,
        "steam_purchase": false,
        "received_for_free": false,
        "written_during_early_access": false,
        "hidden_in_steam_china": true,
        "steam_china_location": ""
    },
    {
        "recommendationid": "143881643",
        "author": {
            "steamid": "76561198259403625",
            "num_games_owned": 135,
            "num_reviews": 4,
            "playtime_forever": 10,
            "playtime_last_two_weeks": 10,
            "playtime_at_review": 10,
            "last_played": 1691756337
        },
        "language": "schinese",
        "review": "我没想到暴雪还敢在steam上线的，还敢让国服的玩家评测的，把魔兽、炉石和守望的战绩、皮肤、好友和进度还给我们！\n守望先锋是个好游戏，但是守望先锋2 和暴雪不是。\n回不去的16年的夏天",
        "timestamp_created": 1691756563,
        "timestamp_updated": 1691756884,
        "voted_up": false,
        "votes_up": 0,
        "votes_funny": 0,
        "weighted_vote_score": 0,
        "comment_count": 0,
        "steam_purchase": false,
        "received_for_free": false,
        "written_during_early_access": false,
        "hidden_in_steam_china": true,
        "steam_china_location": ""
    },
    {
        "recommendationid": "143881642",
        "author": {
            "steamid": "76561199365145272",
            "num_games_owned": 0,
            "num_reviews": 1,
            "playtime_forever": 10,
            "playtime_last_two_weeks": 10,
            "playtime_at_review": 10,
            "last_played": 1691756049
        },
        "language": "schinese",
        "review": "免费游戏不开国服啊，我还有买一个加速器来玩你这个游戏，分期付款了属于是。\n爱玩的人都骂你，我帮你打个榜吧，你和蒸拼一下",
        "timestamp_created": 1691756563,
        "timestamp_updated": 1691756563,
        "voted_up": false,
        "votes_up": 0,
        "votes_funny": 0,
        "weighted_vote_score": 0,
        "comment_count": 0,
        "steam_purchase": false,
        "received_for_free": false,
        "written_during_early_access": false,
        "hidden_in_steam_china": true,
        "steam_china_location": ""
    },
    {
        "recommendationid": "143881641",
        "author": {
            "steamid": "76561198380715776",
            "num_games_owned": 0,
            "num_reviews": 4,
            "playtime_forever": 6,
            "playtime_last_two_weeks": 6,
            "playtime_at_review": 6,
            "last_played": 1691756338
        },
        "language": "schinese",
        "review": "暴雪赶紧爬，你做个牛子吧，比起运营你的这堆谢特乱几把改，做牛子适合你，要不破产算了，fw，别干了",
        "timestamp_created": 1691756562,
        "timestamp_updated": 1691756562,
        "voted_up": false,
        "votes_up": 0,
        "votes_funny": 0,
        "weighted_vote_score": 0,
        "comment_count": 0,
        "steam_purchase": false,
        "received_for_free": false,
        "written_during_early_access": false,
        "hidden_in_steam_china": true,
        "steam_china_location": ""
    },
    {
        "recommendationid": "143881640",
        "author": {
            "steamid": "76561199238326438",
            "num_games_owned": 0,
            "num_reviews": 1,
            "playtime_forever": 5,
            "playtime_last_two_weeks": 5,
            "playtime_at_review": 5,
            "last_played": 1691757884
        },
        "language": "schinese",
        "review": "cnm暴雪",
        "timestamp_created": 1691756562,
        "timestamp_updated": 1691756562,
        "voted_up": false,
        "votes_up": 0,
        "votes_funny": 0,
        "weighted_vote_score": 0,
        "comment_count": 0,
        "steam_purchase": false,
        "received_for_free": false,
        "written_during_early_access": false,
        "hidden_in_steam_china": true,
        "steam_china_location": ""
    },
    {
        "recommendationid": "143881635",
        "author": {
            "steamid": "76561198080178351",
            "num_games_owned": 0,
            "num_reviews": 4,
            "playtime_forever": 30,
            "playtime_last_two_weeks": 30,
            "playtime_at_review": 30,
            "last_played": 1691756523
        },
        "language": "schinese",
        "review": "垃圾",
        "timestamp_created": 1691756557,
        "timestamp_updated": 1691756696,
        "voted_up": false,
        "votes_up": 0,
        "votes_funny": 0,
        "weighted_vote_score": 0,
        "comment_count": 0,
        "steam_purchase": false,
        "received_for_free": false,
        "written_during_early_access": false,
        "hidden_in_steam_china": true,
        "steam_china_location": ""
    },
    {
        "recommendationid": "143881633",
        "author": {
            "steamid": "76561199180954568",
            "num_games_owned": 173,
            "num_reviews": 33,
            "playtime_forever": 7,
            "playtime_last_two_weeks": 7,
            "playtime_at_review": 7,
            "last_played": 1691755526
        },
        "language": "schinese",
        "review": "呃呃我没玩过这游戏，也不知道这游戏错在哪，但是既然大家都打差评那我也下一个来打吧。",
        "timestamp_created": 1691756557,
        "timestamp_updated": 1691756557,
        "voted_up": false,
        "votes_up": 0,
        "votes_funny": 0,
        "weighted_vote_score": 0,
        "comment_count": 0,
        "steam_purchase": false,
        "received_for_free": false,
        "written_during_early_access": false,
        "hidden_in_steam_china": true,
        "steam_china_location": ""
    },
    {
        "recommendationid": "143881632",
        "author": {
            "steamid": "76561198332389630",
            "num_games_owned": 92,
            "num_reviews": 8,
            "playtime_forever": 6,
            "playtime_last_two_weeks": 6,
            "playtime_at_review": 6,
            "last_played": 1691756489
        },
        "language": "schinese",
        "review": "操你妈的还我国服，我要我的吼肩我的怒傻龙我的能量平衡",
        "timestamp_created": 1691756556,
        "timestamp_updated": 1691756556,
        "voted_up": false,
        "votes_up": 0,
        "votes_funny": 0,
        "weighted_vote_score": 0,
        "comment_count": 0,
        "steam_purchase": false,
        "received_for_free": false,
        "written_during_early_access": false,
        "hidden_in_steam_china": true,
        "steam_china_location": ""
    },
    {
        "recommendationid": "143881630",
        "author": {
            "steamid": "76561199145416820",
            "num_games_owned": 66,
            "num_reviews": 1,
            "playtime_forever": 140,
            "playtime_last_two_weeks": 140,
            "playtime_at_review": 19,
            "last_played": 1691762044
        },
        "language": "schinese",
        "review": "暴雪你妈妈什么时候司啊",
        "timestamp_created": 1691756556,
        "timestamp_updated": 1691756556,
        "voted_up": false,
        "votes_up": 0,
        "votes_funny": 0,
        "weighted_vote_score": 0,
        "comment_count": 0,
        "steam_purchase": false,
        "received_for_free": false,
        "written_during_early_access": false,
        "hidden_in_steam_china": true,
        "steam_china_location": ""
    },
    {
        "recommendationid": "143881629",
        "author": {
            "steamid": "76561198114019468",
            "num_games_owned": 179,
            "num_reviews": 14,
            "playtime_forever": 5,
            "playtime_last_two_weeks": 5,
            "playtime_at_review": 5,
            "last_played": 1691756151
        },
        "language": "schinese",
        "review": "暴雪n❤m❤s❤l",
        "timestamp_created": 1691756555,
        "timestamp_updated": 1691756555,
        "voted_up": false,
        "votes_up": 0,
        "votes_funny": 0,
        "weighted_vote_score": 0,
        "comment_count": 0,
        "steam_purchase": false,
        "received_for_free": false,
        "written_during_early_access": false,
        "hidden_in_steam_china": true,
        "steam_china_location": ""
    },
    {
        "recommendationid": "143881628",
        "author": {
            "steamid": "76561199258830810",
            "num_games_owned": 36,
            "num_reviews": 17,
            "playtime_forever": 6,
            "playtime_last_two_weeks": 6,
            "playtime_at_review": 6,
            "last_played": 1691756538
        },
        "language": "schinese",
        "review": "乐色",
        "timestamp_created": 1691756555,
        "timestamp_updated": 1691756555,
        "voted_up": false,
        "votes_up": 0,
        "votes_funny": 0,
        "weighted_vote_score": 0,
        "comment_count": 0,
        "steam_purchase": false,
        "received_for_free": false,
        "written_during_early_access": false,
        "hidden_in_steam_china": true,
        "steam_china_location": ""
    },
    {
        "recommendationid": "143881623",
        "author": {
            "steamid": "76561199118715089",
            "num_games_owned": 26,
            "num_reviews": 1,
            "playtime_forever": 233,
            "playtime_last_two_weeks": 233,
            "playtime_at_review": 103,
            "last_played": 1691763441
        },
        "language": "schinese",
        "review": "垃圾游戏",
        "timestamp_created": 1691756554,
        "timestamp_updated": 1691756554,
        "voted_up": false,
        "votes_up": 0,
        "votes_funny": 0,
        "weighted_vote_score": 0,
        "comment_count": 0,
        "steam_purchase": false,
        "received_for_free": false,
        "written_during_early_access": false,
        "hidden_in_steam_china": true,
        "steam_china_location": ""
    },
    {
        "recommendationid": "143881621",
        "author": {
            "steamid": "76561198976071531",
            "num_games_owned": 71,
            "num_reviews": 3,
            "playtime_forever": 8,
            "playtime_last_two_weeks": 8,
            "playtime_at_review": 8,
            "last_played": 1691756538
        },
        "language": "schinese",
        "review": "sb",
        "timestamp_created": 1691756551,
        "timestamp_updated": 1691756598,
        "voted_up": false,
        "votes_up": 0,
        "votes_funny": 0,
        "weighted_vote_score": 0,
        "comment_count": 0,
        "steam_purchase": false,
        "received_for_free": true,
        "written_during_early_access": false,
        "hidden_in_steam_china": true,
        "steam_china_location": ""
    },
    {
        "recommendationid": "143881617",
        "author": {
            "steamid": "76561199036730477",
            "num_games_owned": 10,
            "num_reviews": 1,
            "playtime_forever": 200,
            "playtime_last_two_weeks": 200,
            "playtime_at_review": 130,
            "last_played": 1691760815
        },
        "language": "schinese",
        "review": "垃圾游戏",
        "timestamp_created": 1691756547,
        "timestamp_updated": 1691756547,
        "voted_up": false,
        "votes_up": 0,
        "votes_funny": 0,
        "weighted_vote_score": 0,
        "comment_count": 0,
        "steam_purchase": false,
        "received_for_free": false,
        "written_during_early_access": false,
        "hidden_in_steam_china": true,
        "steam_china_location": ""
    },
    {
        "recommendationid": "143881615",
        "author": {
            "steamid": "76561199068591864",
            "num_games_owned": 16,
            "num_reviews": 4,
            "playtime_forever": 51,
            "playtime_last_two_weeks": 51,
            "playtime_at_review": 51,
            "last_played": 1691739314
        },
        "language": "schinese",
        "review": "死去的妈是无法复活的",
        "timestamp_created": 1691756545,
        "timestamp_updated": 1691756545,
        "voted_up": false,
        "votes_up": 0,
        "votes_funny": 0,
        "weighted_vote_score": 0,
        "comment_count": 0,
        "steam_purchase": false,
        "received_for_free": false,
        "written_during_early_access": false,
        "hidden_in_steam_china": true,
        "steam_china_location": ""
    },
    {
        "recommendationid": "143881614",
        "author": {
            "steamid": "76561198098664282",
            "num_games_owned": 1257,
            "num_reviews": 89,
            "playtime_forever": 58,
            "playtime_last_two_weeks": 58,
            "playtime_at_review": 50,
            "last_played": 1691772097
        },
        "language": "schinese",
        "review": "我宁愿给你差评也不屑给三国杀差评\n说明我心里还是有你的",
        "timestamp_created": 1691756545,
        "timestamp_updated": 1691756545,
        "voted_up": false,
        "votes_up": 12,
        "votes_funny": 2,
        "weighted_vote_score": "0.644666314125061035",
        "comment_count": 2,
        "steam_purchase": false,
        "received_for_free": false,
        "written_during_early_access": false,
        "hidden_in_steam_china": true,
        "steam_china_location": ""
    },
    {
        "recommendationid": "143881612",
        "author": {
            "steamid": "76561199082630130",
            "num_games_owned": 0,
            "num_reviews": 1,
            "playtime_forever": 246,
            "playtime_last_two_weeks": 246,
            "playtime_at_review": 246,
            "last_played": 1691756481
        },
        "language": "schinese",
        "review": "暴雪恶心人有一手的",
        "timestamp_created": 1691756544,
        "timestamp_updated": 1691756926,
        "voted_up": false,
        "votes_up": 0,
        "votes_funny": 0,
        "weighted_vote_score": 0,
        "comment_count": 0,
        "steam_purchase": false,
        "received_for_free": false,
        "written_during_early_access": false,
        "hidden_in_steam_china": true,
        "steam_china_location": ""
    },
    {
        "recommendationid": "143881609",
        "author": {
            "steamid": "76561198878511445",
            "num_games_owned": 24,
            "num_reviews": 7,
            "playtime_forever": 300,
            "playtime_last_two_weeks": 300,
            "playtime_at_review": 145,
            "last_played": 1691776299
        },
        "language": "ukrainian",
        "review": "Додайте українську мову! Будь ласка.",
        "timestamp_created": 1691756543,
        "timestamp_updated": 1691756543,
        "voted_up": false,
        "votes_up": 0,
        "votes_funny": 0,
        "weighted_vote_score": 0,
        "comment_count": 0,
        "steam_purchase": false,
        "received_for_free": false,
        "written_during_early_access": false,
        "hidden_in_steam_china": true,
        "steam_china_location": ""
    },
    {
        "recommendationid": "143881608",
        "author": {
            "steamid": "76561199443082259",
            "num_games_owned": 4,
            "num_reviews": 3,
            "playtime_forever": 162,
            "playtime_last_two_weeks": 162,
            "playtime_at_review": 162,
            "last_played": 1691756422
        },
        "language": "schinese",
        "review": "cnm",
        "timestamp_created": 1691756542,
        "timestamp_updated": 1691756542,
        "voted_up": false,
        "votes_up": 0,
        "votes_funny": 0,
        "weighted_vote_score": 0,
        "comment_count": 0,
        "steam_purchase": false,
        "received_for_free": false,
        "written_during_early_access": false,
        "hidden_in_steam_china": true,
        "steam_china_location": ""
    },
    {
        "recommendationid": "143881607",
        "author": {
            "steamid": "76561198015291579",
            "num_games_owned": 0,
            "num_reviews": 1,
            "playtime_forever": 79,
            "playtime_last_two_weeks": 79,
            "playtime_at_review": 25,
            "last_played": 1691777080
        },
        "language": "english",
        "review": "Control issues make this unplayable on steam deck. \n\nHoping this gets fixed soon as this would be a fun game to play with my gf. \n\nBut yeah, if you were thinking about playing this on your steam deck, maybe give it a month a month or so and see if it gets patched.",
        "timestamp_created": 1691756541,
        "timestamp_updated": 1691756541,
        "voted_up": false,
        "votes_up": 0,
        "votes_funny": 0,
        "weighted_vote_score": 0,
        "comment_count": 0,
        "steam_purchase": false,
        "received_for_free": false,
        "written_during_early_access": false,
        "hidden_in_steam_china": true,
        "steam_china_location": ""
    },
    {
        "recommendationid": "143881603",
        "author": {
            "steamid": "76561198848547386",
            "num_games_owned": 42,
            "num_reviews": 1,
            "playtime_forever": 26,
            "playtime_last_two_weeks": 26,
            "playtime_at_review": 26,
            "last_played": 1691756428
        },
        "language": "schinese",
        "review": "....................../´¯/)\n....................,/¯../\n.................../..../\n............./´¯/'...'/´¯¯`·¸\n........../'/.../..../......./¨¯\\\n........('(...´...´.... ¯~/'...')\n.........\\.................'...../\n..........''...\\.......... _.·´\n............\\..............(\n..............\\.............\\..",
        "timestamp_created": 1691756538,
        "timestamp_updated": 1691756538,
        "voted_up": false,
        "votes_up": 0,
        "votes_funny": 0,
        "weighted_vote_score": 0,
        "comment_count": 0,
        "steam_purchase": false,
        "received_for_free": false,
        "written_during_early_access": false,
        "hidden_in_steam_china": true,
        "steam_china_location": ""
    },
    {
        "recommendationid": "143881602",
        "author": {
            "steamid": "76561198005775449",
            "num_games_owned": 29,
            "num_reviews": 2,
            "playtime_forever": 41,
            "playtime_last_two_weeks": 41,
            "playtime_at_review": 41,
            "last_played": 1691756492
        },
        "language": "schinese",
        "review": "没什么可说的 国服没了 就差评",
        "timestamp_created": 1691756538,
        "timestamp_updated": 1691756538,
        "voted_up": false,
        "votes_up": 0,
        "votes_funny": 0,
        "weighted_vote_score": 0,
        "comment_count": 0,
        "steam_purchase": false,
        "received_for_free": false,
        "written_during_early_access": false,
        "hidden_in_steam_china": true,
        "steam_china_location": ""
    },
    {
        "recommendationid": "143881601",
        "author": {
            "steamid": "76561198131177268",
            "num_games_owned": 0,
            "num_reviews": 3,
            "playtime_forever": 6,
            "playtime_last_two_weeks": 6,
            "playtime_at_review": 6,
            "last_played": 1691756317
        },
        "language": "schinese",
        "review": "我甚至不愿意重新注册账号，傻逼暴雪赶紧死",
        "timestamp_created": 1691756538,
        "timestamp_updated": 1691756538,
        "voted_up": false,
        "votes_up": 0,
        "votes_funny": 0,
        "weighted_vote_score": 0,
        "comment_count": 0,
        "steam_purchase": false,
        "received_for_free": false,
        "written_during_early_access": false,
        "hidden_in_steam_china": true,
        "steam_china_location": ""
    },
    {
        "recommendationid": "143881600",
        "author": {
            "steamid": "76561198325038403",
            "num_games_owned": 7,
            "num_reviews": 1,
            "playtime_forever": 139,
            "playtime_last_two_weeks": 139,
            "playtime_at_review": 16,
            "last_played": 1691772160
        },
        "language": "schinese",
        "review": "纯路人，希望大家能放下素质，提高攻击性，你可以不喜欢它，但没必要划走，要多一点谩骂，少一点理解和包容，不会喷就复制粘贴，评论区不养闲人\n好评是因为我今天刚入坑，感觉还不错",
        "timestamp_created": 1691756536,
        "timestamp_updated": 1691756536,
        "voted_up": false,
        "votes_up": 0,
        "votes_funny": 0,
        "weighted_vote_score": 0,
        "comment_count": 0,
        "steam_purchase": false,
        "received_for_free": false,
        "written_during_early_access": false,
        "hidden_in_steam_china": true,
        "steam_china_location": ""
    },
    {
        "recommendationid": "143881598",
        "author": {
            "steamid": "76561198082683656",
            "num_games_owned": 43,
            "num_reviews": 10,
            "playtime_forever": 110,
            "playtime_last_two_weeks": 110,
            "playtime_at_review": 6,
            "last_played": 1691771812
        },
        "language": "schinese",
        "review": "暴雪还我国服的雷龙，cnmd",
        "timestamp_created": 1691756535,
        "timestamp_updated": 1691756535,
        "voted_up": false,
        "votes_up": 0,
        "votes_funny": 0,
        "weighted_vote_score": 0,
        "comment_count": 0,
        "steam_purchase": false,
        "received_for_free": false,
        "written_during_early_access": false,
        "hidden_in_steam_china": true,
        "steam_china_location": ""
    },
    {
        "recommendationid": "143881593",
        "author": {
            "steamid": "76561198048534948",
            "num_games_owned": 117,
            "num_reviews": 1,
            "playtime_forever": 49,
            "playtime_last_two_weeks": 49,
            "playtime_at_review": 25,
            "last_played": 1691761264
        },
        "language": "schinese",
        "review": "空姐，能换个游戏吗，想吐。\n那您是需要升级通行证高级版吗？升舱费用是1290。",
        "timestamp_created": 1691756534,
        "timestamp_updated": 1691756868,
        "voted_up": false,
        "votes_up": 0,
        "votes_funny": 0,
        "weighted_vote_score": 0,
        "comment_count": 0,
        "steam_purchase": false,
        "received_for_free": false,
        "written_during_early_access": false,
        "hidden_in_steam_china": true,
        "steam_china_location": ""
    },
    {
        "recommendationid": "143881589",
        "author": {
            "steamid": "76561198326234550",
            "num_games_owned": 0,
            "num_reviews": 7,
            "playtime_forever": 5,
            "playtime_last_two_weeks": 5,
            "playtime_at_review": 5,
            "last_played": 1691756230
        },
        "language": "schinese",
        "review": "all the people wanna starcraft live except sm blizzard",
        "timestamp_created": 1691756533,
        "timestamp_updated": 1691756533,
        "voted_up": false,
        "votes_up": 0,
        "votes_funny": 0,
        "weighted_vote_score": 0,
        "comment_count": 0,
        "steam_purchase": false,
        "received_for_free": false,
        "written_during_early_access": false,
        "hidden_in_steam_china": true,
        "steam_china_location": ""
    },
    {
        "recommendationid": "143881586",
        "author": {
            "steamid": "76561199236902289",
            "num_games_owned": 0,
            "num_reviews": 1,
            "playtime_forever": 18,
            "playtime_last_two_weeks": 18,
            "playtime_at_review": 18,
            "last_played": 1691756488
        },
        "language": "schinese",
        "review": "彼阳的晚意，初升的东曦",
        "timestamp_created": 1691756530,
        "timestamp_updated": 1691756721,
        "voted_up": false,
        "votes_up": 0,
        "votes_funny": 0,
        "weighted_vote_score": 0,
        "comment_count": 0,
        "steam_purchase": false,
        "received_for_free": false,
        "written_during_early_access": false,
        "hidden_in_steam_china": true,
        "steam_china_location": ""
    },
    {
        "recommendationid": "143881584",
        "author": {
            "steamid": "76561198283282938",
            "num_games_owned": 0,
            "num_reviews": 1,
            "playtime_forever": 300,
            "playtime_last_two_weeks": 300,
            "playtime_at_review": 179,
            "last_played": 1691776657
        },
        "language": "english",
        "review": "STOP MAKING BAD REVIEWS! I CAN'T LIKE THEM ALL!",
        "timestamp_created": 1691756530,
        "timestamp_updated": 1691756530,
        "voted_up": false,
        "votes_up": 1,
        "votes_funny": 0,
        "weighted_vote_score": "0.500831961631774902",
        "comment_count": 0,
        "steam_purchase": false,
        "received_for_free": false,
        "written_during_early_access": false,
        "hidden_in_steam_china": true,
        "steam_china_location": ""
    },
    {
        "recommendationid": "143881583",
        "author": {
            "steamid": "76561198334351333",
            "num_games_owned": 0,
            "num_reviews": 7,
            "playtime_forever": 37,
            "playtime_last_two_weeks": 37,
            "playtime_at_review": 21,
            "last_played": 1691760612
        },
        "language": "schinese",
        "review": " 游戏是好游戏  但是暴雪战网的账号验证让这个变成了一坨屎 \n靠迪克亲妈爆炸 骨灰飞扬千万家",
        "timestamp_created": 1691756529,
        "timestamp_updated": 1691756529,
        "voted_up": false,
        "votes_up": 0,
        "votes_funny": 0,
        "weighted_vote_score": 0,
        "comment_count": 0,
        "steam_purchase": false,
        "received_for_free": false,
        "written_during_early_access": false,
        "hidden_in_steam_china": true,
        "steam_china_location": ""
    },
    {
        "recommendationid": "143881582",
        "author": {
            "steamid": "76561198981412564",
            "num_games_owned": 22,
            "num_reviews": 1,
            "playtime_forever": 364,
            "playtime_last_two_weeks": 364,
            "playtime_at_review": 178,
            "last_played": 1691771023
        },
        "language": "schinese",
        "review": "差评\n",
        "timestamp_created": 1691756529,
        "timestamp_updated": 1691756529,
        "voted_up": false,
        "votes_up": 0,
        "votes_funny": 0,
        "weighted_vote_score": 0,
        "comment_count": 0,
        "steam_purchase": false,
        "received_for_free": false,
        "written_during_early_access": false,
        "hidden_in_steam_china": true,
        "steam_china_location": ""
    },
    {
        "recommendationid": "143881577",
        "author": {
            "steamid": "76561198131770594",
            "num_games_owned": 93,
            "num_reviews": 4,
            "playtime_forever": 24,
            "playtime_last_two_weeks": 24,
            "playtime_at_review": 24,
            "last_played": 1691756436
        },
        "language": "english",
        "review": "煞笔暴雪，煞笔烤迪克",
        "timestamp_created": 1691756526,
        "timestamp_updated": 1691756526,
        "voted_up": false,
        "votes_up": 0,
        "votes_funny": 0,
        "weighted_vote_score": 0,
        "comment_count": 0,
        "steam_purchase": false,
        "received_for_free": false,
        "written_during_early_access": false,
        "hidden_in_steam_china": true,
        "steam_china_location": ""
    },
    {
        "recommendationid": "143881573",
        "author": {
            "steamid": "76561198257954224",
            "num_games_owned": 104,
            "num_reviews": 9,
            "playtime_forever": 53,
            "playtime_last_two_weeks": 53,
            "playtime_at_review": 53,
            "last_played": 1691756117
        },
        "language": "schinese",
        "review": "5V5的模式让各个职位的压力变得很大，T基本一掉就意味着满盘皆输，相较之下C的作用变得意义不明，就算将C全部从游戏中剔除只留下T位好像也没有很奇怪。\n个人认为更改为6V6模式增加一个T位可以有效解决这个问题。\n整体游戏娱乐性不足，被强制按照要求选择英雄，也许可以满足竞技性但是难以满足作为游戏的娱乐性。\n个人认为增加一个可以重复选相同英雄的模式可能会很有趣，甚至这个模式可以直接安排在快速模式中的一部分。\n皮肤过于昂贵。\n个人认为可以新增一些比如每升一级就可以获得的抽奖道具，让这个抽奖道具可以抽到皮肤以此来降低大部分皮肤的获取难度。\n\n总而言之··········BYD你个B游戏做的还没16年的时候好玩你他妈越做越回去了不如赶紧去似。还浪费你爹我半个多小时去品尝这坨答辩。滚蛋吧，我玩瓦去了。",
        "timestamp_created": 1691756525,
        "timestamp_updated": 1691756551,
        "voted_up": false,
        "votes_up": 0,
        "votes_funny": 0,
        "weighted_vote_score": 0,
        "comment_count": 0,
        "steam_purchase": false,
        "received_for_free": true,
        "written_during_early_access": false,
        "hidden_in_steam_china": true,
        "steam_china_location": ""
    },
    {
        "recommendationid": "143881571",
        "author": {
            "steamid": "76561198812957633",
            "num_games_owned": 64,
            "num_reviews": 48,
            "playtime_forever": 286,
            "playtime_last_two_weeks": 286,
            "playtime_at_review": 284,
            "last_played": 1691766583
        },
        "language": "schinese",
        "review": "你说的对，但是《守望先锋》归来”是款广受好评的团队射击游戏,舞台设定在光明的未来,有着不断进化的英雄阵容，每位英雄各具特色，战斗紧张刺激，地图遍及全球。可以与好友组队投入惊心动魄的5v5团战，或与全新的强大敌对势力殊死搏斗，现在就与好友组队畅玩吧!",
        "timestamp_created": 1691756524,
        "timestamp_updated": 1691756644,
        "voted_up": false,
        "votes_up": 0,
        "votes_funny": 0,
        "weighted_vote_score": 0,
        "comment_count": 0,
        "steam_purchase": false,
        "received_for_free": true,
        "written_during_early_access": false,
        "hidden_in_steam_china": true,
        "steam_china_location": ""
    },
    {
        "recommendationid": "143881570",
        "author": {
            "steamid": "76561198364078294",
            "num_games_owned": 97,
            "num_reviews": 2,
            "playtime_forever": 32,
            "playtime_last_two_weeks": 32,
            "playtime_at_review": 32,
            "last_played": 1691729423
        },
        "language": "schinese",
        "review": "垃圾暴雪，懂的都懂，SB暴雪滚出中国",
        "timestamp_created": 1691756524,
        "timestamp_updated": 1691756524,
        "voted_up": false,
        "votes_up": 0,
        "votes_funny": 0,
        "weighted_vote_score": 0,
        "comment_count": 0,
        "steam_purchase": false,
        "received_for_free": false,
        "written_during_early_access": false,
        "hidden_in_steam_china": true,
        "steam_china_location": ""
    },
    {
        "recommendationid": "143881568",
        "author": {
            "steamid": "76561198107795838",
            "num_games_owned": 128,
            "num_reviews": 9,
            "playtime_forever": 303,
            "playtime_last_two_weeks": 303,
            "playtime_at_review": 13,
            "last_played": 1691776386
        },
        "language": "schinese",
        "review": "守望先锋1真的很好玩",
        "timestamp_created": 1691756523,
        "timestamp_updated": 1691756523,
        "voted_up": false,
        "votes_up": 0,
        "votes_funny": 0,
        "weighted_vote_score": 0,
        "comment_count": 0,
        "steam_purchase": false,
        "received_for_free": false,
        "written_during_early_access": false,
        "hidden_in_steam_china": true,
        "steam_china_location": ""
    },
    {
        "recommendationid": "143881567",
        "author": {
            "steamid": "76561198150824020",
            "num_games_owned": 0,
            "num_reviews": 1,
            "playtime_forever": 42,
            "playtime_last_two_weeks": 42,
            "playtime_at_review": 42,
            "last_played": 1691755042
        },
        "language": "schinese",
        "review": "没有理由，就为了给个差评",
        "timestamp_created": 1691756522,
        "timestamp_updated": 1691756522,
        "voted_up": false,
        "votes_up": 0,
        "votes_funny": 0,
        "weighted_vote_score": 0,
        "comment_count": 0,
        "steam_purchase": false,
        "received_for_free": false,
        "written_during_early_access": false,
        "hidden_in_steam_china": true,
        "steam_china_location": ""
    },
    {
        "recommendationid": "143881565",
        "author": {
            "steamid": "76561198975631618",
            "num_games_owned": 45,
            "num_reviews": 1,
            "playtime_forever": 14,
            "playtime_last_two_weeks": 14,
            "playtime_at_review": 14,
            "last_played": 1691728514
        },
        "language": "schinese",
        "review": "守望先锋2：毁我游戏期待，强力差评！\n\n我简直无法忍受守望先锋2这款游戏的低劣品质！作为一个曾经痴迷于守望先锋的玩家，我对这款续作感到深度失望。游戏画面虽然稍有改进，但仍然逊色于其他同类游戏。角色设计简直毫无创意，没有一个令人难以忘怀的英雄形象。\n\n平衡问题更是让我愤怒至极！某些英雄简直就是无敌存在，而另一些则被设计成脆弱无比。这种不公平让玩家感到无比的挫败，完全摧毁了游戏的乐趣。开发团队对于玩家的反馈似乎置若罔闻，完全没有采取措施来解决游戏的严重平衡问题。\n\n守望先锋以其独特的团队合作和策略性玩法著称，然而守望先锋2却在这方面彻底失败。游戏模式毫无新意可言，地图设计更是索然无味，缺少战术深度和变化。\n\n总的来说，守望先锋2是一款彻头彻尾的失败之作，彻底毁掉了我对于这个系列的所有期待。我感到愤怒、失望和无奈，希望开发团队能够为他们的低劣表现负起责任，重新审视游戏的问题，并采取强有力的措施来修复这个破烂游戏！\n@涵 去刷",
        "timestamp_created": 1691756522,
        "timestamp_updated": 1691756522,
        "voted_up": false,
        "votes_up": 0,
        "votes_funny": 0,
        "weighted_vote_score": 0,
        "comment_count": 0,
        "steam_purchase": false,
        "received_for_free": false,
        "written_during_early_access": false,
        "hidden_in_steam_china": true,
        "steam_china_location": ""
    },
    {
        "recommendationid": "143881563",
        "author": {
            "steamid": "76561198398684122",
            "num_games_owned": 27,
            "num_reviews": 6,
            "playtime_forever": 122,
            "playtime_last_two_weeks": 122,
            "playtime_at_review": 50,
            "last_played": 1691764073
        },
        "language": "schinese",
        "review": "猫\n\n从前，我养了一只猫，我有十块钱，会用八块钱给它买吃的，经常给它洗澡，它也很粘我。\n\n后来，我带它出去玩，路人觉得它很可爱，他们给它喂猫粮，火腿肠，我很不开心，因为它是我的。我想把它抱回家，可是它挣脱我，冲着给它好吃的人喵喵，我抱了几次他都不跟我走，还挠伤了我，于是我转身就走了.....\n\n后来，偶然在路上遇到了它，它身上脏兮兮的。路人们只会给它好吃的，陪它玩玩，却不会带它回家，给它洗澡。它看到我后就跟着我回家，我把它关在了门外，它在门外喵喵地叫着，叫的我很难受，\n可是我不会再要它了\n。\n\ncat\n\nOnce upon a time, I had a cat, I had ten dollars, I would buy it food for eight dollars, bathe it often, and it was very sticky to me.\n\nLater, I took it out to play, passers-by thought it was cute, they fed it cat food, ham sausage, I was very unhappy because it was mine. I wanted to carry it home, but he broke away from me and meowed at the person who gave it good food, I hugged him a few times and he didn't go with me, and scratched me, so I turned around and left.....\n\nLater, I came across it by chance on the road, and it was dirty. Passers-by will only give it good food and play with it, but they will not take it home and bathe it. It saw me and followed me home, I shut it out, it meowed outside the door, it was very uncomfortable,\nbut I wouldn't want it anymore\n.\n\n\n不是人们抛弃了守望先锋。而是守望先锋不会是玩家的英雄了。再也不会是了。It's not that people abandoned Overwatch. It's that Overwatch won't be the player's hero anymore. Not Anymore.\n守望先锋：归西，给暴雪一点3%的小小震撼\n\n如何在不下载游戏的情况下愉快的打差评\n评测条件：通过挂时长软件添加游戏累计6分钟即可\n\nPC端：\nwatt toolkit（原steam++）\nASF\nSAM\n\n移动端：\n云挂卡APP\n如何从库中移除游戏\n主页 > 帐户 > 许可和产品序列号激活：点击移除即可\n或者\n客服 >> 我想从帐户中移除这款游戏\n\n来点客观评价\n暴雪、考迪克死一死的话估计无数人在刷了，总要谈点客观的，不然会有些自觉中立的人说点未经他人苦，却劝他人善的风凉话\n\n先说公事：\n停更几年，画了N年大饼的守望先锋2就是这玩意？改动还没个版本更新大，这些年员工都在忙什么？办公室性骚扰？看看当年守望2预告CG动画里老玩家的弹幕，现今看来只有2个字：心寒。逼肝骗氪就不说了，反正暴雪现在也就只会这个，我的战役模式呢？信誓旦旦的PVE一拖再拖，张口就是为了玩家更好的体验这些晦涩难懂的词。\n\n再聊私事：\n账号承载着老玩家的青春回忆，见证了和朋友一起欢笑犯糗的时光。你说没就没，这就是您说的为了玩家？向钱看嘛，不寒掺，哪怕您站直了脊梁骨，说几句真话，我对您的鄙夷也能少那么几分，来洗的暴白也会多一点。中国玩家不重要，但中国玩家的真金白银很重要。\n\n\n新玩家的避坑理由\n在这里，你能感受到如同上班一样的游玩快感\n在这里，你会发现皮肤出的比版本更新更加勤快\n在这里，你可以体会到原汁原味的正宗暴雪式傲慢\n在这里，你能够看到无数新的承诺簇拥出的艰难决定\n在这里，你将游玩一个拒绝中国市场和中国玩家的高贵洋产，玩之前，先低头再折腰。\n\n结语：\n再不刷差评，我可要给三国杀打好评了哦",
        "timestamp_created": 1691756522,
        "timestamp_updated": 1691756522,
        "voted_up": false,
        "votes_up": 1,
        "votes_funny": 0,
        "weighted_vote_score": "0.523809552192687988",
        "comment_count": 0,
        "steam_purchase": false,
        "received_for_free": false,
        "written_during_early_access": false,
        "hidden_in_steam_china": true,
        "steam_china_location": ""
    },
    {
        "recommendationid": "143881560",
        "author": {
            "steamid": "76561199090859842",
            "num_games_owned": 41,
            "num_reviews": 4,
            "playtime_forever": 135,
            "playtime_last_two_weeks": 135,
            "playtime_at_review": 94,
            "last_played": 1691758911
        },
        "language": "english",
        "review": "steam://openurl/https://store.steampowered.com/app/440",
        "timestamp_created": 1691756521,
        "timestamp_updated": 1691756521,
        "voted_up": false,
        "votes_up": 0,
        "votes_funny": 0,
        "weighted_vote_score": 0,
        "comment_count": 0,
        "steam_purchase": false,
        "received_for_free": false,
        "written_during_early_access": false,
        "hidden_in_steam_china": true,
        "steam_china_location": ""
    },
    {
        "recommendationid": "143881558",
        "author": {
            "steamid": "76561198118127807",
            "num_games_owned": 6,
            "num_reviews": 1,
            "playtime_forever": 6,
            "playtime_last_two_weeks": 6,
            "playtime_at_review": 6,
            "last_played": 1691756113
        },
        "language": "schinese",
        "review": "临时添加简体中文和验证战网真TM绝了,原本以为会有个态度的,结果就是爱玩不玩,正好给完这个差评直接卸载\n三国杀的你们要是不给差评,我就去三国杀差评,考迪克祝你全家暴毙,留你个孤儿受尽羞辱",
        "timestamp_created": 1691756518,
        "timestamp_updated": 1691756518,
        "voted_up": false,
        "votes_up": 0,
        "votes_funny": 0,
        "weighted_vote_score": 0,
        "comment_count": 0,
        "steam_purchase": false,
        "received_for_free": false,
        "written_during_early_access": false,
        "hidden_in_steam_china": true,
        "steam_china_location": ""
    },
    {
        "recommendationid": "143881557",
        "author": {
            "steamid": "76561198094291322",
            "num_games_owned": 170,
            "num_reviews": 16,
            "playtime_forever": 29,
            "playtime_last_two_weeks": 29,
            "playtime_at_review": 29,
            "last_played": 1691756462
        },
        "language": "french",
        "review": "Overwatch 2 is the biggest joke in terms of video game.",
        "timestamp_created": 1691756517,
        "timestamp_updated": 1691756517,
        "voted_up": false,
        "votes_up": 0,
        "votes_funny": 0,
        "weighted_vote_score": 0,
        "comment_count": 0,
        "steam_purchase": false,
        "received_for_free": false,
        "written_during_early_access": false,
        "hidden_in_steam_china": true,
        "steam_china_location": ""
    },
    {
        "recommendationid": "143881555",
        "author": {
            "steamid": "76561198868245651",
            "num_games_owned": 349,
            "num_reviews": 37,
            "playtime_forever": 19,
            "playtime_last_two_weeks": 19,
            "playtime_at_review": 19,
            "last_played": 1691756326
        },
        "language": "schinese",
        "review": "那一年我收到了召唤，加入了守望先锋。\n现在我也收到了召唤，特地前来打差评！\n暴雪和考迪特就是依托答辩！！！！",
        "timestamp_created": 1691756515,
        "timestamp_updated": 1691756515,
        "voted_up": false,
        "votes_up": 0,
        "votes_funny": 0,
        "weighted_vote_score": 0,
        "comment_count": 0,
        "steam_purchase": false,
        "received_for_free": false,
        "written_during_early_access": false,
        "hidden_in_steam_china": true,
        "steam_china_location": ""
    },
    {
        "recommendationid": "143881553",
        "author": {
            "steamid": "76561198375222953",
            "num_games_owned": 23,
            "num_reviews": 1,
            "playtime_forever": 68,
            "playtime_last_two_weeks": 68,
            "playtime_at_review": 68,
            "last_played": 1691741742
        },
        "language": "schinese",
        "review": "辣鸡暴雪，改麦克雷的名字 纯纯有毛病，那么多玩家说走就走去你妈妈的吻",
        "timestamp_created": 1691756510,
        "timestamp_updated": 1691756510,
        "voted_up": false,
        "votes_up": 0,
        "votes_funny": 0,
        "weighted_vote_score": 0,
        "comment_count": 0,
        "steam_purchase": false,
        "received_for_free": false,
        "written_during_early_access": false,
        "hidden_in_steam_china": true,
        "steam_china_location": ""
    },
    {
        "recommendationid": "143881550",
        "author": {
            "steamid": "76561198110921894",
            "num_games_owned": 322,
            "num_reviews": 15,
            "playtime_forever": 23,
            "playtime_last_two_weeks": 23,
            "playtime_at_review": 23,
            "last_played": 1691756357
        },
        "language": "english",
        "review": "I have been playing overwatch since the closed beta back in 2016, and it was my main game for a good while.\nWith basically every newly released hero, the state of the game deteriorated, causing me to drop the game back in 2018 during the height of the GOATs meta.\nThe announcement of a PvE game with the overwatch characters felt like a breath of fresh air, causing me to pick the game back up in late 2019.\nDespite the annoyances I had with the game, I found that there was still a core of fun, and that every once in a while I had a truly fun match.\nI once again dropped the game after a while due to the sheer staleness of the game, due to the lack of content updates.\nWith the announcement of overwatch 2 PvP, me and my friends once again got interested in the game, and picked it up again.\nTo my (and my friends's) surprise, the game had become fun again! Not as fun as back during the early days, but the annoyances I had seemed to be mostly patched out!\nWith a couple of months of playing overwatch 1 again, we got into the closed beta for overwatch 2, and the change from 6v6 to 5v5 ended up being actually positive in our experience.\nIt freed up the game to be of a much higher pace, and much less shield focussed, although there were some balancing issues with the newest hero at the time, sojourn.\nFor every other hero that I had annoyances with, they were either reworked to be less annoying, or had been nerfed into obscurity.\nFast forward a couple of months and it's time for the actual release of overwatch 2, and the servers are just down for most of the first week, great start.\nWhen I finally do get the chance to play, I realize that not only have they not adressed the issues I had with sojourn, but the time between the beta and actual release has made people realize just how abusable the character (and some of the reworked tanks) really are, and they are taking full advantage of it.\n\"Not a problem, it'll be patched out in a few weeks\", I naively thought.\nBut they had once again falled into the same patterns that had initially caused me to dislike overwatch 1, releasing heroes with next to no regard as to how they would affect the gamestate as a whole and how annoying it might be to play with / against.\nBoth kiriko and lifeweaver fall into characters I have annoyances with, in different areas.\nKiriko is extremely annoying to fight due to her insane movement option, on demand invulnerability, slender hitbox and insane damage output. Whereas Lifeweaver straight up has a tool that can grief teammates harder than an enemy roadhog ever could.\nLet alone the fact that they locked these new heroes behind a battlepass system rather than the old loot box system, which was already heavily criticized.\nThe final nail in the coffin was of course the cancellation of the PvE mode, that was an actual backstabbing of the community.\nThe entire point of the 2 in overwatch 2 was the fact that it would have this great, long and highly customizable PvE campaign mode, that would be extremely replayable and great for just messing around with friends.\nCancelling that completely invalidates the entire point of overwatch 2's existance, and I can't help but wonder what the fuck blizzard is thinking.\nThey have shot themselves in the foot, abandoning their own community for 3 full years only to release half baked content in an objectively worse format in a shameless attempt to milk the wallets of their playerbase even further than they already had.\nI cannot with a good conscience reccomend overwatch 2. I truly wish there was a way to still play overwatch 1, because if I had the choice, that is what I would be playing.",
        "timestamp_created": 1691756508,
        "timestamp_updated": 1691756508,
        "voted_up": false,
        "votes_up": 0,
        "votes_funny": 0,
        "weighted_vote_score": 0,
        "comment_count": 0,
        "steam_purchase": false,
        "received_for_free": false,
        "written_during_early_access": false,
        "hidden_in_steam_china": true,
        "steam_china_location": ""
    },
    {
        "recommendationid": "143881549",
        "author": {
            "steamid": "76561198333119857",
            "num_games_owned": 48,
            "num_reviews": 3,
            "playtime_forever": 491,
            "playtime_last_two_weeks": 491,
            "playtime_at_review": 202,
            "last_played": 1691775836
        },
        "language": "russian",
        "review": "Если тут будет 10 пальцев вверх сделаю косплей на Трейсер. п21",
        "timestamp_created": 1691756507,
        "timestamp_updated": 1691756507,
        "voted_up": true,
        "votes_up": 2,
        "votes_funny": 0,
        "weighted_vote_score": "0.525389969348907471",
        "comment_count": 0,
        "steam_purchase": false,
        "received_for_free": false,
        "written_during_early_access": false,
        "hidden_in_steam_china": true,
        "steam_china_location": ""
    },
    {
        "recommendationid": "143881546",
        "author": {
            "steamid": "76561199282731336",
            "num_games_owned": 3,
            "num_reviews": 2,
            "playtime_forever": 155,
            "playtime_last_two_weeks": 155,
            "playtime_at_review": 155,
            "last_played": 1691742100
        },
        "language": "schinese",
        "review": "守望先锋：归西",
        "timestamp_created": 1691756506,
        "timestamp_updated": 1691756506,
        "voted_up": false,
        "votes_up": 0,
        "votes_funny": 0,
        "weighted_vote_score": 0,
        "comment_count": 0,
        "steam_purchase": false,
        "received_for_free": false,
        "written_during_early_access": false,
        "hidden_in_steam_china": true,
        "steam_china_location": ""
    },
    {
        "recommendationid": "143881545",
        "author": {
            "steamid": "76561199133457437",
            "num_games_owned": 0,
            "num_reviews": 3,
            "playtime_forever": 418,
            "playtime_last_two_weeks": 418,
            "playtime_at_review": 8,
            "last_played": 1691781182
        },
        "language": "schinese",
        "review": "真的6，充钱我是jb",
        "timestamp_created": 1691756506,
        "timestamp_updated": 1691756506,
        "voted_up": false,
        "votes_up": 0,
        "votes_funny": 0,
        "weighted_vote_score": 0,
        "comment_count": 0,
        "steam_purchase": false,
        "received_for_free": false,
        "written_during_early_access": false,
        "hidden_in_steam_china": true,
        "steam_china_location": ""
    },
    {
        "recommendationid": "143881544",
        "author": {
            "steamid": "76561198200764433",
            "num_games_owned": 85,
            "num_reviews": 3,
            "playtime_forever": 8,
            "playtime_last_two_weeks": 8,
            "playtime_at_review": 8,
            "last_played": 1691756361
        },
        "language": "schinese",
        "review": "⠀⢀⣤⣶⣶⣤⡀⠀⠀\n⠀⠀⠀⠀⠀⠀⠀⠀⣾⣿⣿⣿⣿⣿⡄⠀\n⠀⠀⠀⠀⠀⠀⠀⠀⠹⣿⣿⣿⣿⡿⠁⠀\n⠀⠀⠀⠀⠀⠀⠀⠀⠀⠈⠉⠉⠉⠀⠀⠀\n⠀⠀⠀⠀⠀⠀⠀⣰⣿⣿⣿⣦⠀⠀⠀⠀\n⠀⠀⠀⠀⠀⠀⣰⣿⣿⣿⣿⣿⠀⠀⠀⠀\n⠀⠀⠀⠀⠀⢰⣿⣿⣿⣿⣿⣿⡀⠀⠀⠀\n⠀⠀⠀⠀⢠⣿⣿⣿⣿⡿⣿⣿⣧⣀⠀⠀\n⠀⠀⠀⠀⢺⣿⣿⣿⣿⣧⣬⣻⢿⣿⣿⡦\n⠀⠀⠀⠀⠀⠙⠻⠿⢿⣿⣿⣿⣿⡏⠛⠁\n⠀⠀⠀⣀⠀⠀⠀⠀⠀⠀⣽⣿⡿⠁⠀⠀\n⠀⢀⡠⣿⣷⣤⡀⠀⠀⢸⣿⣿⠃⠀⠀⠀\n⠰⠿⠿⠿⠿⠿⠇⠀⠠⠿⠿⠏⠀⠀⠀⠀",
        "timestamp_created": 1691756503,
        "timestamp_updated": 1691756503,
        "voted_up": false,
        "votes_up": 0,
        "votes_funny": 0,
        "weighted_vote_score": 0,
        "comment_count": 0,
        "steam_purchase": false,
        "received_for_free": false,
        "written_during_early_access": false,
        "hidden_in_steam_china": true,
        "steam_china_location": ""
    },
    {
        "recommendationid": "143881542",
        "author": {
            "steamid": "76561198099106186",
            "num_games_owned": 161,
            "num_reviews": 3,
            "playtime_forever": 111,
            "playtime_last_two_weeks": 111,
            "playtime_at_review": 23,
            "last_played": 1691781327
        },
        "language": "schinese",
        "review": "好玩",
        "timestamp_created": 1691756501,
        "timestamp_updated": 1691756501,
        "voted_up": false,
        "votes_up": 0,
        "votes_funny": 0,
        "weighted_vote_score": 0,
        "comment_count": 0,
        "steam_purchase": false,
        "received_for_free": false,
        "written_during_early_access": false,
        "hidden_in_steam_china": true,
        "steam_china_location": ""
    },
    {
        "recommendationid": "143881541",
        "author": {
            "steamid": "76561198325785190",
            "num_games_owned": 124,
            "num_reviews": 89,
            "playtime_forever": 386,
            "playtime_last_two_weeks": 386,
            "playtime_at_review": 182,
            "last_played": 1691768881
        },
        "language": "latam",
        "review": "Estan tan desesperados que lo pusieron en Steam xD",
        "timestamp_created": 1691756501,
        "timestamp_updated": 1691756501,
        "voted_up": false,
        "votes_up": 0,
        "votes_funny": 0,
        "weighted_vote_score": 0,
        "comment_count": 0,
        "steam_purchase": false,
        "received_for_free": false,
        "written_during_early_access": false,
        "hidden_in_steam_china": true,
        "steam_china_location": ""
    },
    {
        "recommendationid": "143881540",
        "author": {
            "steamid": "76561198067217997",
            "num_games_owned": 0,
            "num_reviews": 94,
            "playtime_forever": 18,
            "playtime_last_two_weeks": 18,
            "playtime_at_review": 18,
            "last_played": 1691756455
        },
        "language": "koreana",
        "review": "아니 하이퍼 fps에 물개가 없다고?????\n물개 내줄 때 까지 평가 고쳐 줄 생각없다 ㅋ",
        "timestamp_created": 1691756501,
        "timestamp_updated": 1691756501,
        "voted_up": false,
        "votes_up": 0,
        "votes_funny": 0,
        "weighted_vote_score": 0,
        "comment_count": 0,
        "steam_purchase": false,
        "received_for_free": false,
        "written_during_early_access": false,
        "hidden_in_steam_china": true,
        "steam_china_location": ""
    },
    {
        "recommendationid": "143881538",
        "author": {
            "steamid": "76561198061238365",
            "num_games_owned": 161,
            "num_reviews": 10,
            "playtime_forever": 85,
            "playtime_last_two_weeks": 85,
            "playtime_at_review": 85,
            "last_played": 1691755580
        },
        "language": "english",
        "review": "bad game",
        "timestamp_created": 1691756500,
        "timestamp_updated": 1691756500,
        "voted_up": false,
        "votes_up": 0,
        "votes_funny": 0,
        "weighted_vote_score": 0,
        "comment_count": 0,
        "steam_purchase": false,
        "received_for_free": false,
        "written_during_early_access": false,
        "hidden_in_steam_china": true,
        "steam_china_location": ""
    },
    {
        "recommendationid": "143881531",
        "author": {
            "steamid": "76561198365689379",
            "num_games_owned": 25,
            "num_reviews": 1,
            "playtime_forever": 43,
            "playtime_last_two_weeks": 43,
            "playtime_at_review": 21,
            "last_played": 1691759004
        },
        "language": "schinese",
        "review": "暴雪你mu没了",
        "timestamp_created": 1691756495,
        "timestamp_updated": 1691756495,
        "voted_up": false,
        "votes_up": 0,
        "votes_funny": 0,
        "weighted_vote_score": 0,
        "comment_count": 0,
        "steam_purchase": false,
        "received_for_free": false,
        "written_during_early_access": false,
        "hidden_in_steam_china": true,
        "steam_china_location": ""
    }
]